Workbook

Sheet Update
A1: Id | B1: Start time | C1: Completion time | D1: Email | E1: Name | F1: Nama Pelapor | G1: Nama Proyek | H1: Periode Progres | I1: Presentase Aktual Progress | J1: Presentase Rencana Progress | K1: Presentase BAB 1 | L1: Presentase BAB 2 | M1: Presentase BAB 3 | N1: Presentase BAB 4 | O1: Presentase BAB 5 | P1: Presentase BAB 6 | Q1: Presentase BAB 7 | R1: Presentase BAB 8 | S1: Presentase BAB 9 | T1: Presentase BAB 10 | U1: Presentase BAB 11 | V1: Presentase BAB 12 | W1: Presentase BAB 13 | X1: Presentase BAB 14 | Y1: Presentase BAB 15 | Z1: Presentase BAB 16 | AA1: Link Dokumentasi Video Drone | AB1: Link Dokumentasi Foto | AC1: Link Orthophoto | AD1: Link Reality Modeling | AE1: Periode Issue | AF1: Issue | AG1: Koordinat Proyek | AH1: Lat | AI1: Long | AJ1: Status | AK1: __PowerAppsId__
A2: 761 | B2: 44569 | C2: =B2 -> 44569 | D2: Esri_Anonymous | E2: M Saifudin Ashari | F2: =E2 -> M Saifudin Ashari | G2: Jalan Tol Bocimi Seksi 2 | H2: 44591 | I2: 76.851 | J2: 78.251 | K2: 0.915 | L2: 0.865 | M2: 0.864 | N2: 0.885 | O2: 0.423 | P2: 0.516 | Q2: 0.54 | R2: 0.44 | S2: 0.889 | T2: 0.019 | U2: 0.513 | V2: 0 | W2: 0 | X2: 0.31 | Y2: 0 | AG2: =VLOOKUP(OfficeForms.Table[[#This Row],[Nama Proyek]],'Nama Proyek'!$D$2:$G$29,4,0) -> -6.80675464,106.785366 | AK2: 01295f48-974d-48b4-b138-23608606326d
A3: 762 | B3: 44569 | C3: =B3 -> 44569 | D3: Esri_Anonymous | E3: M Saifudin Ashari | F3: =E3 -> M Saifudin Ashari | G3: Jalan Tol Bocimi Seksi 2 | H3: 44619 | I3: 77.925 | J3: 81.748 | K3: 0.915 | L3: 0.865 | M3: 0.872 | N3: 0.885 | O3: 0.428 | P3: 0.518 | Q3: 0.54 | R3: 0.461 | S3: 0.901 | T3: 0.019 | U3: 0.516 | V3: 0 | W3: 0 | X3: 0.31 | Y3: 0 | AG3: =VLOOKUP(OfficeForms.Table[[#This Row],[Nama Proyek]],'Nama Proyek'!$D$2:$G$29,4,0) -> -6.80675464,106.785366 | AK3: 08fb3e28-02c7-48ac-a421-4bed199374e4
A4: 763 | B4: 44569 | C4: =B4 -> 44569 | D4: Esri_Anonymous | E4: M Saifudin Ashari | F4: =E4 -> M Saifudin Ashari | G4: Jalan Tol Bocimi Seksi 2 | H4: 44647 | I4: 79.017 | J4: 87.502 | K4: 0.915 | L4: 0.865 | M4: 0.883 | N4: 0.885 | O4: 0.439 | P4: 0.518 | Q4: 0.54 | R4: 0.475 | S4: 0.905 | T4: 0.233 | U4: 0.525 | V4: 0 | W4: 0 | X4: 0.31 | Y4: 0 | AG4: =VLOOKUP(OfficeForms.Table[[#This Row],[Nama Proyek]],'Nama Proyek'!$D$2:$G$29,4,0) -> -6.80675464,106.785366 | AK4: 500ce746-deba-47b9-9ae4-7498cd048bba
A5: 813 | B5: 44569 | C5: =B5 -> 44569 | D5: Esri_Anonymous | E5: M Saifudin Ashari | F5: =E5 -> M Saifudin Ashari | G5: Jalan Tol Bocimi Seksi 2 | H5: 44675 | I5: 79.052 | J5: 79.208 | K5: 0.901 | L5: 0.987 | M5: 0.891 | N5: 0.874 | O5: 0.445 | P5: 0.519 | Q5: 0.54 | R5: 0.485 | S5: 0.892 | T5: 0.451 | U5: 0.536 | V5: 0 | W5: 0 | X5: 0.305 | Y5: 0 | AG5: =VLOOKUP(OfficeForms.Table[[#This Row],[Nama Proyek]],'Nama Proyek'!$D$2:$G$29,4,0) -> -6.80675464,106.785366 | AK5: 1205050c-ff5d-4ff0-9aa0-81d8fbcf4f08
A6: 814 | B6: 44569 | C6: =B6 -> 44569 | D6: Esri_Anonymous | E6: M Saifudin Ashari | F6: =E6 -> M Saifudin Ashari | G6: Jalan Tol Bocimi Seksi 2 | H6: 44710 | I6: 79.502 | J6: 82.926 | K6: 0.901 | L6: 0.987 | M6: 0.901 | N6: 0.874 | O6: 0.457 | P6: 0.538 | Q6: 0.544 | R6: 0.487 | S6: 0.892 | T6: 0.451 | U6: 0.543 | V6: 0 | W6: 0 | X6: 0.305 | Y6: 0 | AG6: =VLOOKUP(OfficeForms.Table[[#This Row],[Nama Proyek]],'Nama Proyek'!$D$2:$G$29,4,0) -> -6.80675464,106.785366 | AK6: c68e95c8-1f3f-4599-8951-5f49ec41862c
A7: 815 | B7: 44569 | C7: =B7 -> 44569 | D7: Esri_Anonymous | E7: M Saifudin Ashari | F7: =E7 -> M Saifudin Ashari | G7: Jalan Tol Bocimi Seksi 2 | H7: 44735 | I7: 80.824 | J7: 87.407 | K7: 0.901 | L7: 0.987 | M7: 0.918 | N7: 0.874 | O7: 0.467 | P7: 0.547 | Q7: 0.558 | R7: 0.501 | S7: 0.907 | T7: 0.497 | U7: 0.557 | V7: 0 | W7: 0 | X7: 0.305 | Y7: 0 | AG7: =VLOOKUP(OfficeForms.Table[[#This Row],[Nama Proyek]],'Nama Proyek'!$D$2:$G$29,4,0) -> -6.80675464,106.785366 | AK7: e1421f62-7e4c-428e-b28a-90197d1bff3a
A8: 236 | B8: 44569 | C8: =B8 -> 44569 | D8: andi.firdaus_waskitakarya | E8: Basuki Rahmat Hakim | F8: Basuki Rahmat Hakim | G8: Jalan Long Semamu - Long Bawan 2 (JOP 70%) | H8: 44763 | I8: 28.886 | J8: 30.71 | K8: 0 | L8: 27.379 | M8: 0 | N8: 0 | O8: 0 | P8: 0 | Q8: 0 | R8: 0.231 | S8: 0 | T8: 0 | U8: 0 | V8: 0 | W8: 0 | X8: 0 | Y8: 0 | AG8: =VLOOKUP(OfficeForms.Table[[#This Row],[Nama Proyek]],'Nama Proyek'!$D$2:$G$29,4,0) -> 3.76047575,115.89977678 | AK8: 655347d4-a916-4a70-bd8c-c68781c0163f
A9: 243 | B9: 44569 | C9: =B9 -> 44569 | D9: Esri_Anonymous | E9: Basuki Rahmat Hakim | F9: =E9 -> Basuki Rahmat Hakim | G9: Jalan Long Semamu - Long Bawan 2 (JOP 70%) | H9: 44763 | I9: 28.886 | J9: 30.71 | K9: 0 | L9: 27.379 | M9: 0 | N9: 0 | O9: 0 | P9: 0 | Q9: 0 | R9: 0.231 | S9: 0 | T9: 0 | U9: 0 | V9: 0 | W9: 0 | X9: 0 | Y9: 0 | AG9: =VLOOKUP(OfficeForms.Table[[#This Row],[Nama Proyek]],'Nama Proyek'!$D$2:$G$29,4,0) -> 3.76047575,115.89977678 | AK9: 0fbc4e87-ee39-4edb-8909-ced495f1002e
A10: 180 | B10: 44569 | C10: =B10 -> 44569 | D10: Esri_Anonymous | E10: Riezky Ibnu Prasetyo | F10: =E10 -> Riezky Ibnu Prasetyo | G10: Jalan Tol Cibitung - Cilincing Seksi 2 | H10: 44766 | I10: 83.915 | J10: 0 | K10: 0 | L10: 0 | M10: 0 | N10: 0.003 | O10: 0 | P10: 0 | Q10: 0 | R10: 0.024 | S10: 2.811 | T10: 0 | U10: 0 | V10: 0 | W10: 0 | X10: 0 | Y10: 0 | AG10: =VLOOKUP(OfficeForms.Table[[#This Row],[Nama Proyek]],'Nama Proyek'!$D$2:$G$29,4,0) -> -6.13491053,106.93675986 | AK10: c6a5273c-ee19-49b2-81e0-8e030882b53c
A11: 166 | B11: 44569 | C11: =B11 -> 44569 | D11: Esri_Anonymous | E11: Haryo Widiandoko | F11: =E11 -> Haryo Widiandoko | G11: Jalan Tol Japek II Selatan Paket 3 | H11: 44771 | I11: 75.869 | J11: 79.785 | K11: 27.49 | L11: 76.97 | M11: 73.02 | N11: 77.83 | O11: 39.17 | P11: 68.16 | Q11: 71.86 | R11: 66 | S11: 97.88 | T11: 0 | U11: 23.83 | V11: 6.3 | W11: 0 | X11: 78.49 | Y11: 0 | AG11: =VLOOKUP(OfficeForms.Table[[#This Row],[Nama Proyek]],'Nama Proyek'!$D$2:$G$29,4,0) -> -6.42873464,107.19897003 | AK11: 19d374c5-f708-4999-bf5b-03c18c3f703c
A12: 82 | B12: 44569 | C12: =B12 -> 44569 | D12: Esri_Anonymous | E12: Alfian Budi Prasetya | F12: =E12 -> Alfian Budi Prasetya | G12: Jalan Akses dan Kawasan Avasta | H12: 44773 | I12: 21.582 | J12: 94.148 | K12: 17.804 | L12: 1.322 | M12: 0.287 | N12: 0.249 | O12: 0 | P12: 0 | Q12: 0 | R12: 0 | S12: 0 | T12: 0 | U12: 0 | V12: 0 | W12: 0 | X12: 0 | Y12: 0 | AF12: Buangan Galian Boundary Drain | AG12: =VLOOKUP(OfficeForms.Table[[#This Row],[Nama Proyek]],'Nama Proyek'!$D$2:$G$29,4,0) -> -6.12967558,107.07321308 | AK12: 3c7732a5-9cc7-4aaf-b3c2-ffbe6b8be0d3
A13: 865 | B13: 44569 | C13: =B13 -> 44569 | D13: Esri_Anonymous | E13: M Saifudin Ashari | F13: =E13 -> M Saifudin Ashari | G13: Jalan Tol Bocimi Seksi 2 | H13: 44773 | I13: 83.896 | J13: 92.387 | K13: 0.901 | L13: 0.987 | M13: 0.927 | N13: 0.877 | O13: 0.481 | P13: 0.603 | Q13: 0.629 | R13: 0.536 | S13: 0.939 | T13: 0.769 | U13: 0.567 | V13: 0 | W13: 0 | X13: 0.305 | Y13: 0 | AG13: =VLOOKUP(OfficeForms.Table[[#This Row],[Nama Proyek]],'Nama Proyek'!$D$2:$G$29,4,0) -> -6.80675464,106.785366 | AK13: 16d4afbe-7b98-48a8-98ae-c62a16e8e0b8
A14: 83 | B14: 44569 | C14: =B14 -> 44569 | D14: Esri_Anonymous | E14: Alfian Budi Prasetya | F14: =E14 -> Alfian Budi Prasetya | G14: Jalan Akses dan Kawasan Avasta | I14: 0 | J14: 0 | K14: 0 | L14: 0 | M14: 0 | N14: 0 | O14: 0 | P14: 0 | Q14: 0 | R14: 0 | S14: 0 | T14: 0 | U14: 0 | V14: 0 | W14: 0 | X14: 0 | Y14: 0 | AE14: 29/07/22 | AG14: =VLOOKUP(OfficeForms.Table[[#This Row],[Nama Proyek]],'Nama Proyek'!$D$2:$G$29,4,0) -> -6.12967558,107.07321308 | AK14: c197a9bb-6395-4e63-a980-725996468e2f
A15: 186 | B15: 44569 | C15: =B15 -> 44569 | D15: Esri_Anonymous | E15: Nizar Zulkarnain | F15: =E15 -> Nizar Zulkarnain | G15: Jalan Tol Cimanggis Cibitung Seksi 2 | I15: 0 | J15: 0 | K15: 0 | L15: 0 | M15: 0 | N15: 0 | O15: 0 | P15: 0 | Q15: 0 | R15: 0 | S15: 0 | T15: 0 | U15: 0 | V15: 0 | W15: 0 | X15: 0 | Y15: 0 | AC15: https://ptwaskita-my.sharepoint.com/:i:/g/personal/nizar_zulkarnain_waskita_co_id/EaUVyfC89PVBr9PeS1_jnhgB8f_-NXtHOoYDIYkFKtM6yg?e=aVNgqT | AF15: Steel Box Girder Elevated Transyogi masih belum dikirim seluruhnya secara kontinu oleh BMI. Persiapan erection masih terkendala alat support erection masih belum disetting untuk erection. | AG15: =VLOOKUP(OfficeForms.Table[[#This Row],[Nama Proyek]],'Nama Proyek'!$D$2:$G$29,4,0) -> -6.35008011,107.02324233 | AK15: 8641390f-d4d3-416d-b55e-344112a1a6f8
A16: 251 | B16: 44569 | C16: =B16 -> 44569 | D16: Esri_Anonymous | E16: Riezky Ibnu Prasetyo | F16: =E16 -> Riezky Ibnu Prasetyo | G16: Jalan Tol Cibitung - Cilincing Seksi 2 | I16: 0 | J16: 0 | K16: 0 | L16: 0 | M16: 0 | N16: 0 | O16: 0 | P16: 0 | Q16: 0 | R16: 0 | S16: 0 | T16: 0 | U16: 0 | V16: 0 | W16: 0 | X16: 0 | Y16: 0 | AA16: https://drive.google.com/drive/u/2/folders/1TPNPPyr5KG-BOau-0_zVewD5BD4OGclD | AB16: https://drive.google.com/drive/u/2/folders/1TPNPPyr5KG-BOau-0_zVewD5BD4OGclD | AC16: https://ptwaskita-my.sharepoint.com/:f:/g/personal/fahmi_waskita_co_id/EmNyIicQoohIvNQFWujff_kB_kDxEQuFgLeC7aB4Z_3QSA?e=2BxylI | AD16: https://ptwaskita-my.sharepoint.com/:f:/g/personal/fahmi_waskita_co_id/EmNyIicQoohIvNQFWujff_kB_kDxEQuFgLeC7aB4Z_3QSA?e=2BxylI | AG16: =VLOOKUP(OfficeForms.Table[[#This Row],[Nama Proyek]],'Nama Proyek'!$D$2:$G$29,4,0) -> -6.13491053,106.93675986 | AK16: d94abc25-bcdd-4d2c-bf59-d0b8f0c91a69
A17: 252 | B17: 44569 | C17: =B17 -> 44569 | D17: Esri_Anonymous | E17: Riezky Ibnu Prasetyo | F17: =E17 -> Riezky Ibnu Prasetyo | G17: Jalan Tol Cibitung - Cilincing Seksi 2 | I17: 0 | J17: 0 | K17: 0 | L17: 0 | M17: 0 | N17: 0 | O17: 0 | P17: 0 | Q17: 0 | R17: 0 | S17: 0 | T17: 0 | U17: 0 | V17: 0 | W17: 0 | X17: 0 | Y17: 0 | AA17: https://drive.google.com/file/d/15Jh9CL6Dd-vDUCFdby6THO7TZ1Tx8len/view?usp=sharing | AG17: =VLOOKUP(OfficeForms.Table[[#This Row],[Nama Proyek]],'Nama Proyek'!$D$2:$G$29,4,0) -> -6.13491053,106.93675986 | AK17: 71f31616-6be4-4207-b82d-9b4732f76118
A18: 207 | B18: 44573 | C18: =B18 -> 44573 | D18: Esri_Anonymous | E18: Haryo Widiandoko | F18: =E18 -> Haryo Widiandoko | G18: Jalan Tol Japek II Selatan Paket 3 | H18: 44893 | I18: 69.837 | J18: 71.156 | K18: 0.112 | L18: 0.128 | M18: 20.685 | N18: 2.035 | O18: 2.355 | P18: 0.052 | Q18: 0.585 | R18: 10.308 | S18: 30.691 | T18: 0.612 | U18: 1.297 | V18: 0.031 | W18: 0 | X18: 0.739 | Y18: 0 | AG18: =VLOOKUP(OfficeForms.Table[[#This Row],[Nama Proyek]],'Nama Proyek'!$D$2:$G$29,4,0) -> -6.42873464,107.19897003 | AK18: 853cb85b-63bb-4a20-8e0b-adf4d84ac83f
A19: 642 | B19: 44573 | C19: =B19 -> 44573 | D19: Esri_Anonymous | E19: Banyu Purwita | F19: =E19 -> Banyu Purwita | G19: Fly Over Simpang Sekip - Palembang (JOI 65%) | I19: 0 | J19: 0 | K19: 0 | L19: 0 | M19: 0 | N19: 0 | O19: 0 | P19: 0 | Q19: 0 | R19: 0 | S19: 0 | T19: 0 | U19: 0 | V19: 0 | W19: 0 | X19: 0 | Y19: 0 | AA19: https://ptwaskita-my.sharepoint.com/:f:/g/personal/banyu_purwita_waskita_co_id/EqTjUHNq3YxAussMGuMB4SsB4kHg8l1RoWIAsL3jYUQ9ig?e=wkoXee | AB19: https://ptwaskita-my.sharepoint.com/:f:/g/personal/banyu_purwita_waskita_co_id/EqTjUHNq3YxAussMGuMB4SsB4kHg8l1RoWIAsL3jYUQ9ig?e=wkoXee | AC19: https://ptwaskita-my.sharepoint.com/:f:/g/personal/banyu_purwita_waskita_co_id/EqTjUHNq3YxAussMGuMB4SsB4kHg8l1RoWIAsL3jYUQ9ig?e=wkoXee | AD19: https://ptwaskita-my.sharepoint.com/:f:/g/personal/banyu_purwita_waskita_co_id/EqTjUHNq3YxAussMGuMB4SsB4kHg8l1RoWIAsL3jYUQ9ig?e=wkoXee | AG19: =VLOOKUP(OfficeForms.Table[[#This Row],[Nama Proyek]],'Nama Proyek'!$D$2:$G$29,4,0) -> -2.95293103,104.75455094 | AK19: 89b87f51-6f64-40d2-b72a-c60f36713864
A20: 253 | B20: 44600 | C20: =B20 -> 44600 | D20: Esri_Anonymous | E20: Fajar Sodiq Febriansyah | F20: =E20 -> Fajar Sodiq Febriansyah | G20: Jalan Tol Paspro Seksi 4 | H20: 44735 | I20: 27.1694 | J20: 55.7068 | K20: 0.161 | L20: 0.0804 | M20: 13.0715 | N20: 0.2864 | O20: 0.0446 | P20: 0.0053 | Q20: 0.0006 | R20: 0.3957 | S20: 15.6692 | T20: 0 | U20: 0.0819 | V20: 0 | W20: 0 | X20: 0.1042 | Y20: 0 | AG20: =VLOOKUP(OfficeForms.Table[[#This Row],[Nama Proyek]],'Nama Proyek'!$D$2:$G$29,4,0) -> -7.82225167,113.29968319 | AK20: 79671d44-4c09-4490-b3d4-56864afc245b
A21: 254 | B21: 44600 | C21: =B21 -> 44600 | D21: Esri_Anonymous | E21: Ajik Prastiyo | F21: =E21 -> Ajik Prastiyo | G21: Jalan Tol Paspro Seksi 4 | H21: 44773 | I21: 44.002827 | J21: 48.305322 | K21: 0.29875857 | L21: 0.09688374 | M21: 20.333593 | N21: 0.4063855 | O21: 0.09679439 | P21: 0.01773914 | Q21: 0.00071883 | R21: 0.86200131 | S21: 21.364516 | T21: 0 | U21: 0.1002754 | V21: 0 | W21: 0.03659606 | X21: 0.12110213 | Y21: 0 | AF21: Pekerjaan Beton Struktur Jumlah BP sudah terpenuhi, flow material (pasir, semen, split) belum terpenuhi | AG21: =VLOOKUP(OfficeForms.Table[[#This Row],[Nama Proyek]],'Nama Proyek'!$D$2:$G$29,4,0) -> -7.82225167,113.29968319 | AK21: 3769f100-aa01-4ba6-b8a3-c10358e5be4e
A22: 259 | B22: 44600 | C22: =B22 -> 44600 | D22: Esri_Anonymous | E22: Nungki Herdiana | F22: =E22 -> Nungki Herdiana | G22: Proyek Peningkatan Jalan Sp. Siligita - Kempinski | H22: 44775 | I22: 66.31 | J22: 66.34 | K22: 78.29 | L22: 98.07 | M22: 94.31 | N22: 7.66 | O22: 52.04 | P22: 184.85 | Q22: 59.98 | R22: 0 | S22: 0 | T22: 0 | U22: 0 | V22: 0 | W22: 0 | X22: 0 | Y22: 0 | AF22: Progress pekerjaan item Cipta Karya 10.09 % belum dapat ditagihkan terkait dengan HPS item baru dan spesifikasi teknis untuk dasar pembayaran. | AG22: =VLOOKUP(OfficeForms.Table[[#This Row],[Nama Proyek]],'Nama Proyek'!$D$2:$G$29,4,0) -> #N/A | AK22: 8ec8e0fd-939e-45bd-b4c4-3dba6514f144
A23: 255 | B23: 44600 | C23: =B23 -> 44600 | D23: Esri_Anonymous | E23: Ajik Prastiyo | F23: =E23 -> Ajik Prastiyo | G23: Jalan Tol Paspro Seksi 4 | I23: 0 | J23: 0 | K23: 0 | L23: 0 | M23: 0 | N23: 0 | O23: 0 | P23: 0 | Q23: 0 | R23: 0 | S23: 0 | T23: 0 | U23: 0 | V23: 0 | W23: 0 | X23: 0 | Y23: 0 | AE23: 44569 | AF23: Kekurangan fleet untuk melakukan pekerjaan tanah sesuai target | AG23: =VLOOKUP(OfficeForms.Table[[#This Row],[Nama Proyek]],'Nama Proyek'!$D$2:$G$29,4,0) -> -7.82225167,113.29968319 | AK23: 0d0edcf6-4a51-4c67-895d-a686a6e81e92
A24: 256 | B24: 44600 | C24: =B24 -> 44600 | D24: Esri_Anonymous | E24: Ajik Prastiyo | F24: =E24 -> Ajik Prastiyo | G24: Jalan Tol Paspro Seksi 4 | I24: 0 | J24: 0 | K24: 0 | L24: 0 | M24: 0 | N24: 0 | O24: 0 | P24: 0 | Q24: 0 | R24: 0 | S24: 0 | T24: 0 | U24: 0 | V24: 0 | W24: 0 | X24: 0 | Y24: 0 | AE24: 44569 | AF24: Adanya beberapa lahan konsinyasi yang belum bebas dengan nilai UGK sebesar 10,83 M, pada lokasi IC STA 03+150 – 03+500, yang mengganggu mobilisasi pekerjaan. | AG24: =VLOOKUP(OfficeForms.Table[[#This Row],[Nama Proyek]],'Nama Proyek'!$D$2:$G$29,4,0) -> -7.82225167,113.29968319 | AK24: fe9b9e08-32ae-4cf2-8e70-64a9d38d0277
A25: 257 | B25: 44600 | C25: =B25 -> 44600 | D25: Esri_Anonymous | E25: Ajik Prastiyo | F25: =E25 -> Ajik Prastiyo | G25: Jalan Tol Paspro Seksi 4 | I25: 0 | J25: 0 | K25: 0 | L25: 0 | M25: 0 | N25: 0 | O25: 0 | P25: 0 | Q25: 0 | R25: 0 | S25: 0 | T25: 0 | U25: 0 | V25: 0 | W25: 0 | X25: 0 | Y25: 0 | AE25: 31/07/22 | AG25: =VLOOKUP(OfficeForms.Table[[#This Row],[Nama Proyek]],'Nama Proyek'!$D$2:$G$29,4,0) -> -7.82225167,113.29968319 | AK25: 96664f5d-0d79-4fe6-a9b9-50bd634f2668
A26: 260 | B26: 44600 | C26: =B26 -> 44600 | D26: Esri_Anonymous | E26: Nungki Herdiana | F26: =E26 -> Nungki Herdiana | G26: Proyek Peningkatan Jalan Sp. Siligita - Kempinski | I26: 0 | J26: 0 | K26: 0 | L26: 0 | M26: 0 | N26: 0 | O26: 0 | P26: 0 | Q26: 0 | R26: 0 | S26: 0 | T26: 0 | U26: 0 | V26: 0 | W26: 0 | X26: 0 | Y26: 0 | AE26: 44600 | AF26: Addendum final menunggu addendum item ke Cipta Karya | AG26: =VLOOKUP(OfficeForms.Table[[#This Row],[Nama Proyek]],'Nama Proyek'!$D$2:$G$29,4,0) -> #N/A | AK26: 2aa8c67d-d1fd-4c23-bbf9-7476588f45b4
A27: 261 | B27: 44600 | C27: =B27 -> 44600 | D27: Esri_Anonymous | E27: Nungki Herdiana | F27: =E27 -> Nungki Herdiana | G27: Proyek Peningkatan Jalan Sp. Siligita - Kempinski | I27: 0 | J27: 0 | K27: 0 | L27: 0 | M27: 0 | N27: 0 | O27: 0 | P27: 0 | Q27: 0 | R27: 0 | S27: 0 | T27: 0 | U27: 0 | V27: 0 | W27: 0 | X27: 0 | Y27: 0 | AE27: 44600 | AF27: Keterlambatan pengiriman material Ducting dikarenakan WPB tidak memiliki kemampuann finansial untuk membayar expedisi. | AG27: =VLOOKUP(OfficeForms.Table[[#This Row],[Nama Proyek]],'Nama Proyek'!$D$2:$G$29,4,0) -> #N/A | AK27: 6166c7e5-06d4-40c4-9da5-7e6822445089
A28: 262 | B28: 44600 | C28: =B28 -> 44600 | D28: Esri_Anonymous | E28: Nungki Herdiana | F28: =E28 -> Nungki Herdiana | G28: Proyek Peningkatan Jalan Sp. Siligita - Kempinski | I28: 0 | J28: 0 | K28: 0 | L28: 0 | M28: 0 | N28: 0 | O28: 0 | P28: 0 | Q28: 0 | R28: 0 | S28: 0 | T28: 0 | U28: 0 | V28: 0 | W28: 0 | X28: 0 | Y28: 0 | AE28: 44600 | AF28: Pada area Jalan Siligita - Kempinski sering dilakukan event, baik dari pihak instansi maupun kegiatan kenegaraan sehingga Polisi menghentikan aktifitas proyek saat tamu menuju lokasi. | AG28: =VLOOKUP(OfficeForms.Table[[#This Row],[Nama Proyek]],'Nama Proyek'!$D$2:$G$29,4,0) -> #N/A | AK28: 34bee91d-8648-42ab-87bc-94cad0314020
A29: 263 | B29: 44600 | C29: =B29 -> 44600 | D29: Esri_Anonymous | E29: Nungki Herdiana | F29: =E29 -> Nungki Herdiana | G29: Proyek Peningkatan Jalan Sp. Siligita - Kempinski | I29: 0 | J29: 0 | K29: 0 | L29: 0 | M29: 0 | N29: 0 | O29: 0 | P29: 0 | Q29: 0 | R29: 0 | S29: 0 | T29: 0 | U29: 0 | V29: 0 | W29: 0 | X29: 0 | Y29: 0 | AE29: 44600 | AF29: Pekerjan Pengaspalan mengalami keterlambatan dikarenakan subkon pekerjaan aspal tidak memiliki kemampuan finansial yang baik | AG29: =VLOOKUP(OfficeForms.Table[[#This Row],[Nama Proyek]],'Nama Proyek'!$D$2:$G$29,4,0) -> #N/A | AK29: ee12e7a8-ab13-42e3-babb-8b31431e7c1c
A30: 264 | B30: 44600 | C30: =B30 -> 44600 | D30: Esri_Anonymous | E30: Nungki Herdiana | F30: =E30 -> Nungki Herdiana | G30: Proyek Peningkatan Jalan Sp. Siligita - Kempinski | I30: 0 | J30: 0 | K30: 0 | L30: 0 | M30: 0 | N30: 0 | O30: 0 | P30: 0 | Q30: 0 | R30: 0 | S30: 0 | T30: 0 | U30: 0 | V30: 0 | W30: 0 | X30: 0 | Y30: 0 | AE30: 44600 | AG30: =VLOOKUP(OfficeForms.Table[[#This Row],[Nama Proyek]],'Nama Proyek'!$D$2:$G$29,4,0) -> #N/A | AK30: ee7a42ce-6524-429f-858e-4f27d20b88d0
A31: 477 | B31: 44600 | C31: =B31 -> 44600 | D31: Esri_Anonymous | E31: Haryo Widiandoko | F31: =E31 -> Haryo Widiandoko | G31: Jalan Tol Japek II Selatan Paket 3 | I31: 0 | J31: 0 | K31: 0 | L31: 0 | M31: 0 | N31: 0 | O31: 0 | P31: 0 | Q31: 0 | R31: 0 | S31: 0 | T31: 0 | U31: 0 | V31: 0 | W31: 0 | X31: 0 | Y31: 0 | AA31: https://drive.google.com/file/d/1_m11qHP04rEw3MA-Ex-QOBusDt3_tSDo/view?usp=sharing | AB31: https://drive.google.com/file/d/1AhBYaMU89WHRri0kBpF5ucBZBmfRVGba/view?usp=sharing | AC31: https://ptwaskita-my.sharepoint.com/:f:/r/personal/fahmi_waskita_co_id/Documents/BIM%20-%20INFRA%202/Project/WKINF2%20-%20D32C19006%20(Jakarta%20-%20Cikampek%20II%20Selatan%20Paket%203)/3.%20PUBLISHED/9.%20REALITY%20MODELING/202207%20-%20Juli%202022/SS%2 | AD31: https://ptwaskita-my.sharepoint.com/:f:/r/personal/fahmi_waskita_co_id/Documents/BIM%20-%20INFRA%202/Project/WKINF2%20-%20D32C19006%20(Jakarta%20-%20Cikampek%20II%20Selatan%20Paket%203)/3.%20PUBLISHED/9.%20REALITY%20MODELING/202207%20-%20Juli%202022?csf= | AG31: =VLOOKUP(OfficeForms.Table[[#This Row],[Nama Proyek]],'Nama Proyek'!$D$2:$G$29,4,0) -> -6.42873464,107.19897003 | AK31: 2e8eaf7c-f39d-4660-b564-95301d839974
A32: 867 | B32: 44603 | C32: =B32 -> 44603 | D32: Esri_Anonymous | E32: Muhamad Saifudin Ashari | F32: =E32 -> Muhamad Saifudin Ashari | G32: Jalan Tol Bocimi Seksi 2 | H32: 44834 | I32: 87.597 | J32: 89.257 | K32: 0.985 | L32: 0.878 | M32: 0.959 | N32: 0.982 | O32: 0.629 | P32: 0.818 | Q32: 0.822 | R32: 0.677 | S32: 0.946 | T32: 0.826 | U32: 0.51 | V32: 0 | W32: 0 | X32: 0.32 | Y32: 0 | AG32: =VLOOKUP(OfficeForms.Table[[#This Row],[Nama Proyek]],'Nama Proyek'!$D$2:$G$29,4,0) -> -6.80675464,106.785366 | AK32: 0e9bf1c8-34fd-4480-ae73-d21fc719798f
A33: 367 | B33: 44603 | C33: =B33 -> 44603 | D33: Esri_Anonymous | E33: Nungki Herdiana | F33: =E33 -> Nungki Herdiana | G33: Proyek Peningkatan Jalan Sp. Siligita - Kempinski | H33: 44854 | I33: 100 | J33: 100 | K33: 100 | L33: 100 | M33: 100 | N33: 100 | O33: 100 | P33: 100 | Q33: 100 | R33: 0 | S33: 100 | T33: 0 | U33: 0 | V33: 0 | W33: 0 | X33: 0 | Y33: 0 | AF33: Keterlambatan terbitnya Jaminan Pemeliharaan dikarenakan belum disahkan ADD 3 oleh para pihak | AG33: =VLOOKUP(OfficeForms.Table[[#This Row],[Nama Proyek]],'Nama Proyek'!$D$2:$G$29,4,0) -> #N/A | AK33: a3ae426c-b68b-430c-94bc-0144fcf21e0d
A34: 203 | B34: 44603 | C34: =B34 -> 44603 | D34: Esri_Anonymous | E34: Haryo Widiandoko | F34: =E34 -> Haryo Widiandoko | G34: Jalan Tol Japek II Selatan Paket 3 | H34: 44862 | I34: 84.578 | J34: 85.969 | K34: 27.49 | L34: 76.97 | M34: 84.51 | N34: 87.07 | O34: 43.52 | P34: 68.16 | Q34: 83.55 | R34: 81.3 | S34: 103.41 | T34: 0 | U34: 31.76 | V34: 6.3 | W34: 0 | X34: 78.49 | Y34: 0 | AG34: =VLOOKUP(OfficeForms.Table[[#This Row],[Nama Proyek]],'Nama Proyek'!$D$2:$G$29,4,0) -> -6.42873464,107.19897003 | AK34: 0e050198-432c-4fe3-a1a6-964ecb201086
A35: 248 | B35: 44603 | C35: =B35 -> 44603 | D35: Esri_Anonymous | E35: Muhamad Saifudin Ashari | F35: Muhamad Saifudin Ashari | G35: Jalan Tol Bocimi Seksi 2 | I35: 0 | J35: 0 | K35: 0 | L35: 0 | M35: 0 | N35: 0 | O35: 0 | P35: 0 | Q35: 0 | R35: 0 | S35: 0 | T35: 0 | U35: 0 | V35: 0 | W35: 0 | X35: 0 | Y35: 0 | AE35: 17/10/22 | AF35: Semua girder (PCI & Steel Box Girder) JU Akses Cibadak telah selesai tererection | AG35: =VLOOKUP(OfficeForms.Table[[#This Row],[Nama Proyek]],'Nama Proyek'!$D$2:$G$29,4,0) -> -6.80675464,106.785366 | AK35: 1d11f478-5f50-4682-b3cb-160711d6a1f6
A36: 368 | B36: 44603 | C36: =B36 -> 44603 | D36: Esri_Anonymous | E36: Nungki Herdiana | F36: =E36 -> Nungki Herdiana | G36: Proyek Peningkatan Jalan Sp. Siligita - Kempinski | I36: 0 | J36: 0 | K36: 0 | L36: 0 | M36: 0 | N36: 0 | O36: 0 | P36: 0 | Q36: 0 | R36: 0 | S36: 0 | T36: 0 | U36: 0 | V36: 0 | W36: 0 | X36: 0 | Y36: 0 | AE36: 20/10/22 | AF36: Adanya genangan air di Sta. 4+100 jalan siligita-Kempinski (depan hotel vouk) dikarenakan elevasi badan jalan rencana di bawah elevasi tanah warga yang tidak mau dibebaskan dan curah hujan yang tinggi. | AG36: =VLOOKUP(OfficeForms.Table[[#This Row],[Nama Proyek]],'Nama Proyek'!$D$2:$G$29,4,0) -> #N/A | AK36: 58899984-e84f-4c92-aeb2-b82a58c8b1c7
A37: 369 | B37: 44603 | C37: =B37 -> 44603 | D37: Esri_Anonymous | E37: Nungki Herdiana | F37: =E37 -> Nungki Herdiana | G37: Proyek Peningkatan Jalan Sp. Siligita - Kempinski | I37: 0 | J37: 0 | K37: 0 | L37: 0 | M37: 0 | N37: 0 | O37: 0 | P37: 0 | Q37: 0 | R37: 0 | S37: 0 | T37: 0 | U37: 0 | V37: 0 | W37: 0 | X37: 0 | Y37: 0 | AE37: 20/10/22 | AF37: Fungsional Nataru Bocimi Seksi 2 dilaksanakan pada 23 sd 31 Des 2022 dan arus balik Nataru pada 1 sd 2 Jan 2023 | AG37: =VLOOKUP(OfficeForms.Table[[#This Row],[Nama Proyek]],'Nama Proyek'!$D$2:$G$29,4,0) -> #N/A | AK37: f646259a-2611-4fce-8fdb-e901a4a2fb47
A38: 371 | B38: 44603 | C38: =B38 -> 44603 | D38: Esri_Anonymous | E38: YECKASTORO JANUWISESA | F38: =E38 -> YECKASTORO JANUWISESA | G38: Proyek Peningkatan Jalan Sp. Siligita - Kempinski | I38: 0 | J38: 0 | K38: 0 | L38: 0 | M38: 0 | N38: 0 | O38: 0 | P38: 0 | Q38: 0 | R38: 0 | S38: 0 | T38: 0 | U38: 0 | V38: 0 | W38: 0 | X38: 0 | Y38: 0 | AA38: https://drive.google.com/file/d/1cRh0mkRmYQapfKQc5MJNXwwddD5qArPv/view?usp=share_link | AE38: =[1]!OfficeForms.Table[[#This Row],[Waktu selesai]] -> #REF! | AF38: Bocimi Seksi 2 dibuka sebagai jalur fungsional Libur Natal 2022 dan tahun baru 2023 pada 23 Desember sd 2 Januari 2023 | AG38: =VLOOKUP(OfficeForms.Table[[#This Row],[Nama Proyek]],'Nama Proyek'!$D$2:$G$29,4,0) -> #N/A | AK38: 91dbe8c0-e4cf-4058-a133-1ad625dc4ab2
A39: 373 | B39: 44603 | C39: =B39 -> 44603 | D39: Esri_Anonymous | E39: YECKASTORO JANUWISESA | F39: =E39 -> YECKASTORO JANUWISESA | G39: Proyek Peningkatan Jalan Sp. Siligita - Kempinski | I39: 0 | J39: 0 | K39: 0 | L39: 0 | M39: 0 | N39: 0 | O39: 0 | P39: 0 | Q39: 0 | R39: 0 | S39: 0 | T39: 0 | U39: 0 | V39: 0 | W39: 0 | X39: 0 | Y39: 0 | AA39: https://drive.google.com/file/d/1cRh0mkRmYQapfKQc5MJNXwwddD5qArPv/view?usp=share_link | AB39: https://drive.google.com/file/d/1c7FMSLa45dM05wRH_D1oEtUcV1F66J80/view?usp=share_link; https://drive.google.com/file/d/1O4I1zuyJeyjr40DshCJOerpZy95cC5f6/view?usp=share_link; https://drive.google.com/file/d/1JLTZnVinxoGH9GaDIaGbI0uU4I-Dfb1j/view?usp=share | AE39: =[1]!OfficeForms.Table[[#This Row],[Waktu selesai]] -> #REF! | AG39: =VLOOKUP(OfficeForms.Table[[#This Row],[Nama Proyek]],'Nama Proyek'!$D$2:$G$29,4,0) -> #N/A | AK39: 616a9607-fda0-408a-8bf0-c14df13084a4
A40: 698 | B40: 44628 | C40: =B40 -> 44628 | D40: Esri_Anonymous | E40: Nizar Zulkarnain | F40: =E40 -> Nizar Zulkarnain | G40: Jalan Tol Cimanggis Cibitung Seksi 2 | H40: 44773 | I40: 70.426 | J40: 71.455 | K40: 58.12 | L40: 55.31 | M40: 80.94 | N40: 77.67 | O40: 44.5 | P40: 58 | Q40: 53.55 | R40: 47.27 | S40: 81.89 | T40: 79.88 | U40: 27.81 | V40: 10.74 | W40: 0 | X40: 98.36 | Y40: 4.1 | AF40: PLN : tiang dan pln yg masih berada dilokasi menggangu jalannya progress pekerjaan PDAM : pipa PDAM yang belum terkoneksi di lahan Bea Cukai mengakibatkan pipa eksisting di lokasi frontage belum bisa dibongkar dan berdampak pek timbunan, aggregate A, di | AG40: =VLOOKUP(OfficeForms.Table[[#This Row],[Nama Proyek]],'Nama Proyek'!$D$2:$G$29,4,0) -> -6.35008011,107.02324233 | AK40: 51346516-6302-4696-bea3-35570b1cd623
A41: 187 | B41: 44628 | C41: =B41 -> 44628 | D41: Esri_Anonymous | E41: Nizar Zulkarnain | F41: =E41 -> Nizar Zulkarnain | G41: Jalan Tol Cimanggis Cibitung Seksi 2 | I41: 0 | J41: 0 | K41: 0 | L41: 0 | M41: 0 | N41: 0 | O41: 0 | P41: 0 | Q41: 0 | R41: 0 | S41: 0 | T41: 0 | U41: 0 | V41: 0 | W41: 0 | X41: 0 | Y41: 0 | AE41: 18/07/22 | AG41: =VLOOKUP(OfficeForms.Table[[#This Row],[Nama Proyek]],'Nama Proyek'!$D$2:$G$29,4,0) -> -6.35008011,107.02324233 | AK41: e033a1ad-9c09-47e5-992e-ee3392a2aeaf
A42: 188 | B42: 44628 | C42: =B42 -> 44628 | D42: Esri_Anonymous | E42: Nizar Zulkarnain | F42: =E42 -> Nizar Zulkarnain | G42: Jalan Tol Cimanggis Cibitung Seksi 2 | I42: 0 | J42: 0 | K42: 0 | L42: 0 | M42: 0 | N42: 0 | O42: 0 | P42: 0 | Q42: 0 | R42: 0 | S42: 0 | T42: 0 | U42: 0 | V42: 0 | W42: 0 | X42: 0 | Y42: 0 | AA42: https://drive.google.com/file/d/1hoIbrWfJndjcZUPcrl68H17tdaf7syBe/view?usp=sharing | AB42: https://ptwaskita-my.sharepoint.com/personal/fahmi_waskita_co_id/_layouts/15/onedrive.aspx?ga=1&id=%2Fpersonal%2Ffahmi%5Fwaskita%5Fco%5Fid%2FDocuments%2FBIM%20%2D%20INFRA%202%2FProject%2FWKINF2%20%2D%201316022%20%28Jalan%20Tol%20Cimanggis%20%2D%20Cibitun | AG42: =VLOOKUP(OfficeForms.Table[[#This Row],[Nama Proyek]],'Nama Proyek'!$D$2:$G$29,4,0) -> -6.35008011,107.02324233 | AK42: 5e3db6df-3d63-4799-a886-3ac9cb0ccacb
A43: 866 | B43: 44630 | C43: =B43 -> 44630 | D43: Esri_Anonymous | E43: Muhamad Saifudin Ashari | F43: =E43 -> Muhamad Saifudin Ashari | G43: Jalan Tol Bocimi Seksi 2 | H43: 44804 | I43: 84.871 | J43: 85.504 | K43: 0.985 | L43: 0.878 | M43: 0.98 | N43: 1.025 | O43: 0.593 | P43: 0.662 | Q43: 0.079 | R43: 0.618 | S43: 0.926 | T43: 0.698 | U43: 0.481 | V43: 0 | W43: 0 | X43: 0.32 | Y43: 0 | AG43: =VLOOKUP(OfficeForms.Table[[#This Row],[Nama Proyek]],'Nama Proyek'!$D$2:$G$29,4,0) -> -6.80675464,106.785366 | AK43: 548449c6-c7c7-46f6-b5e0-143878b92724
A44: 211 | B44: 44630 | C44: =B44 -> 44630 | D44: Esri_Anonymous | E44: Utomo Aryowibowo | F44: =E44 -> Utomo Aryowibowo | G44: Jalan Tol Cibitung - Cilincing Seksi 2 | H44: 44826 | I44: 99.25 | J44: 99.36 | K44: 0 | L44: -0.001 | M44: 0.152 | N44: 0.241 | O44: 0 | P44: 0 | Q44: 0 | R44: 2.752 | S44: 77.112 | T44: 0 | U44: 0.23 | V44: 0.377 | W44: 0 | X44: 0.518 | Y44: 0 | AG44: =VLOOKUP(OfficeForms.Table[[#This Row],[Nama Proyek]],'Nama Proyek'!$D$2:$G$29,4,0) -> -6.13491053,106.93675986 | AK44: ee4c7b34-8960-4bec-982b-58a66df11094
A45: 328 | B45: 44630 | C45: =B45 -> 44630 | D45: Esri_Anonymous | E45: Alfian Budi Prasetya | F45: =E45 -> Alfian Budi Prasetya | G45: Jalan Akses dan Kawasan Avasta | H45: 44829 | I45: 20.968 | J45: 31.725 | K45: 16.14634 | L45: 2.1021509 | M45: 0.47968198 | N45: 0.37529074 | O45: 0 | P45: 0 | Q45: 0 | R45: 0.25392507 | S45: 0 | T45: 0 | U45: 0 | V45: 0 | W45: 0 | X45: 0 | Y45: 0 | AF45: Terdapat material sisa untuk jalan akses alat berat | AG45: =VLOOKUP(OfficeForms.Table[[#This Row],[Nama Proyek]],'Nama Proyek'!$D$2:$G$29,4,0) -> -6.12967558,107.07321308 | AK45: 60035a60-e6a1-45e7-b36b-aeff6c1ebb6f
A46: 327 | B46: 44630 | C46: =B46 -> 44630 | D46: Esri_Anonymous | E46: Ajik Prastiyo | F46: =E46 -> Ajik Prastiyo | G46: Jalan Tol Paspro Seksi 4 | H46: 44834 | I46: 60.0369 | J46: 59.4559 | K46: 0.40100447 | L46: 0.09872552 | M46: 26.086527 | N46: 0.53471209 | O46: 0.4043796 | P46: 0.07549005 | Q46: 0.00506673 | R46: 4.9610378 | S46: 26.351492 | T46: 0 | U46: 0.4946593 | V46: 0.01556435 | W46: 0.03659606 | X46: 0.1433672 | Y46: 0 | AG46: =VLOOKUP(OfficeForms.Table[[#This Row],[Nama Proyek]],'Nama Proyek'!$D$2:$G$29,4,0) -> -7.82225167,113.29968319 | AK46: 1269cb65-5584-46f9-ae77-901e87fa9bfc
A47: 246 | B47: 44630 | C47: =B47 -> 44630 | D47: Esri_Anonymous | E47: Muhamad Saifudin Ashari | F47: =E47 -> Muhamad Saifudin Ashari | G47: Jalan Tol Bocimi Seksi 2 | I47: 0 | J47: 0 | K47: 0 | L47: 0 | M47: 0 | N47: 0 | O47: 0 | P47: 0 | Q47: 0 | R47: 0 | S47: 0 | T47: 0 | U47: 0 | V47: 0 | W47: 0 | X47: 0 | Y47: 0 | AE47: 44690 | AG47: =VLOOKUP(OfficeForms.Table[[#This Row],[Nama Proyek]],'Nama Proyek'!$D$2:$G$29,4,0) -> -6.80675464,106.785366 | AK47: 22d17ce8-3d94-478e-a907-55056661c10f
A48: 319 | B48: 44630 | C48: =B48 -> 44630 | D48: Esri_Anonymous | E48: Utomo Aryowibowo | F48: =E48 -> Utomo Aryowibowo | G48: Jalan Tol Cibitung - Cilincing Seksi 2 | I48: 0 | J48: 0 | K48: 0 | L48: 0 | M48: 0 | N48: 0 | O48: 0 | P48: 0 | Q48: 0 | R48: 0 | S48: 0 | T48: 0 | U48: 0 | V48: 0 | W48: 0 | X48: 0 | Y48: 0 | AA48: https://drive.google.com/drive/folders/1XP4tP4vhQZanKddI5hCtkCGLmAnnllVv | AB48: https://drive.google.com/drive/folders/1XP4tP4vhQZanKddI5hCtkCGLmAnnllVv | AC48: https://ptwaskita-my.sharepoint.com/:f:/g/personal/fahmi_waskita_co_id/EuvJAl6OzyhGmExRzRp9MRsBdC9rQKLBxVL0hYZ_7jWu6w?e=tSHMIR | AD48: https://ptwaskita-my.sharepoint.com/:f:/g/personal/fahmi_waskita_co_id/EuvJAl6OzyhGmExRzRp9MRsBdC9rQKLBxVL0hYZ_7jWu6w?e=tSHMIR | AF48: Penyelesaian MC100 dan As Built Drawing untuk Cibcil 2 dan 4, rencana deadline pada 4 Juni 2023 | AG48: =VLOOKUP(OfficeForms.Table[[#This Row],[Nama Proyek]],'Nama Proyek'!$D$2:$G$29,4,0) -> -6.13491053,106.93675986 | AK48: 124928be-07ea-4876-902f-5e7607ddde16
A49: 325 | B49: 44630 | C49: =B49 -> 44630 | D49: Esri_Anonymous | E49: Ajik Prastiyo | F49: =E49 -> Ajik Prastiyo | G49: Jalan Tol Paspro Seksi 4 | I49: 0 | J49: 0 | K49: 0 | L49: 0 | M49: 0 | N49: 0 | O49: 0 | P49: 0 | Q49: 0 | R49: 0 | S49: 0 | T49: 0 | U49: 0 | V49: 0 | W49: 0 | X49: 0 | Y49: 0 | AE49: 44630 | AF49: Target pengecoran Bulan September per hari 700 m3, terealisasi dari skema SBO 520 m3/hari. Supply material SBO khusunya material (Pasir & Split) masih belum tercapai sesuai rencana. | AG49: =VLOOKUP(OfficeForms.Table[[#This Row],[Nama Proyek]],'Nama Proyek'!$D$2:$G$29,4,0) -> -7.82225167,113.29968319 | AK49: e101d633-eb60-43f6-a761-193c271081f8
A50: 326 | B50: 44630 | C50: =B50 -> 44630 | D50: Esri_Anonymous | E50: Ajik Prastiyo | F50: =E50 -> Ajik Prastiyo | G50: Jalan Tol Paspro Seksi 4 | I50: 0 | J50: 0 | K50: 0 | L50: 0 | M50: 0 | N50: 0 | O50: 0 | P50: 0 | Q50: 0 | R50: 0 | S50: 0 | T50: 0 | U50: 0 | V50: 0 | W50: 0 | X50: 0 | Y50: 0 | AE50: 44630 | AG50: =VLOOKUP(OfficeForms.Table[[#This Row],[Nama Proyek]],'Nama Proyek'!$D$2:$G$29,4,0) -> -7.82225167,113.29968319 | AK50: f39f2a27-cd34-4b09-9477-3761f017bc4e
A51: 329 | B51: 44630 | C51: =B51 -> 44630 | D51: Esri_Anonymous | E51: Alfian Budi Prasetya | F51: =E51 -> Alfian Budi Prasetya | G51: Jalan Akses dan Kawasan Avasta | I51: 0 | J51: 0 | K51: 0 | L51: 0 | M51: 0 | N51: 0 | O51: 0 | P51: 0 | Q51: 0 | R51: 0 | S51: 0 | T51: 0 | U51: 0 | V51: 0 | W51: 0 | X51: 0 | Y51: 0 | AE51: 23/09/22 | AG51: =VLOOKUP(OfficeForms.Table[[#This Row],[Nama Proyek]],'Nama Proyek'!$D$2:$G$29,4,0) -> -6.12967558,107.07321308 | AK51: 7584c050-edf2-4cba-bf40-0efea5d7cfe2
A52: 174 | B52: 44661 | C52: =B52 -> 44661 | D52: Esri_Anonymous | E52: Haryo Widiandoko | F52: =E52 -> Haryo Widiandoko | G52: Jalan Tol Japek II Selatan Paket 3 | H52: 44832 | I52: 81.916 | J52: 86.468 | K52: 27.49 | L52: 76.97 | M52: 81.34 | N52: 79.79 | O52: 42.57 | P52: 68.16 | Q52: 80.1 | R52: 75.65 | S52: 101.91 | T52: 0 | U52: 30.82 | V52: 6.3 | W52: 0 | X52: 78.49 | Y52: 0 | AG52: =VLOOKUP(OfficeForms.Table[[#This Row],[Nama Proyek]],'Nama Proyek'!$D$2:$G$29,4,0) -> -6.42873464,107.19897003 | AK52: 1c9cb0b2-5271-4040-9a6e-8abd0e4a90b0
A53: 478 | B53: 44661 | C53: =B53 -> 44661 | D53: Esri_Anonymous | E53: Haryo Widiandoko | F53: =E53 -> Haryo Widiandoko | G53: Jalan Tol Japek II Selatan Paket 3 | I53: 0 | J53: 0 | K53: 0 | L53: 0 | M53: 0 | N53: 0 | O53: 0 | P53: 0 | Q53: 0 | R53: 0 | S53: 0 | T53: 0 | U53: 0 | V53: 0 | W53: 0 | X53: 0 | Y53: 0 | AA53: https://drive.google.com/file/d/1fRqlbo0NVLg_Qsenzj383P4Xi6NYVwpB/view?usp=drivesdk | AB53: https://drive.google.com/file/d/1mDHBnWIDVb6kMhDI8-ROGpKTzDo48MM5/view?usp=drivesdk | AC53: https://ptwaskita-my.sharepoint.com/:f:/r/personal/fahmi_waskita_co_id/Documents/BIM%20-%20INFRA%202/Project/WKINF2%20-%20D32C19006%20(Jakarta%20-%20Cikampek%20II%20Selatan%20Paket%203)/3.%20PUBLISHED/9.%20REALITY%20MODELING/202209%20-%20September?csf=1& | AD53: https://ptwaskita-my.sharepoint.com/:f:/r/personal/fahmi_waskita_co_id/Documents/BIM%20-%20INFRA%202/Project/WKINF2%20-%20D32C19006%20(Jakarta%20-%20Cikampek%20II%20Selatan%20Paket%203)/3.%20PUBLISHED/9.%20REALITY%20MODELING/202209%20-%20September?csf=1& | AG53: =VLOOKUP(OfficeForms.Table[[#This Row],[Nama Proyek]],'Nama Proyek'!$D$2:$G$29,4,0) -> -6.42873464,107.19897003 | AK53: fe2f2f7f-0c8a-4ddc-a213-2a2a0c662016
A54: 50 | B54: 44662 | C54: =B54 -> 44662 | D54: Esri_Anonymous | E54: Banyu Purwita | F54: =E54 -> Banyu Purwita | G54: Fly Over Simpang Sekip - Palembang (JOI 65%) | H54: 44868 | I54: 25.486 | J54: 28.465 | K54: 0 | L54: 0 | M54: 0.963 | N54: 0 | O54: 10.222 | P54: 0 | Q54: 0 | R54: 0 | S54: 13.066 | T54: 0 | U54: 0 | V54: 0 | W54: 0 | X54: 0 | Y54: 0 | AG54: =VLOOKUP(OfficeForms.Table[[#This Row],[Nama Proyek]],'Nama Proyek'!$D$2:$G$29,4,0) -> -2.95293103,104.75455094 | AK54: aacbd036-8539-462b-8ad3-55f6114654f3
A55: 122 | B55: 44673 | C55: =B55 -> 44673 | D55: Esri_Anonymous | E55: Utomo Aryowibowo | F55: =E55 -> Utomo Aryowibowo | G55: Jalan Tol Cibitung - Cilincing Seksi 2 | H55: 44665 | I55: 83.42 | J55: 84.3 | K55: 0 | L55: 0 | M55: 0 | N55: 0 | O55: 0 | P55: 0 | Q55: 0 | R55: 0 | S55: 0 | T55: 0 | U55: 0 | V55: 0 | W55: 0 | X55: 0 | Y55: 0 | AG55: =VLOOKUP(OfficeForms.Table[[#This Row],[Nama Proyek]],'Nama Proyek'!$D$2:$G$29,4,0) -> -6.13491053,106.93675986 | AK55: 51724b83-fc8d-4665-8c2c-80e64197f643
A56: 96 | B56: 44673 | C56: =B56 -> 44673 | D56: Esri_Anonymous | E56: ISNAEN DWI SANJOYO | F56: =E56 -> ISNAEN DWI SANJOYO | G56: Jalan Tol Becakayu 2A Ujung | I56: 0 | J56: 0 | K56: 0 | L56: 0 | M56: 0 | N56: 0 | O56: 0 | P56: 0 | Q56: 0 | R56: 0 | S56: 0 | T56: 0 | U56: 0 | V56: 0 | W56: 0 | X56: 0 | Y56: 0 | AA56: https://ptwaskita-my.sharepoint.com/:f:/g/personal/becakayu2aujung_waskita_co_id/EtKhMYsK2zBGvQMyfV2-WRsBC3ZCjB_RnOw0cJzRnU-lAg?e=ifnktz | AB56: https://ptwaskita-my.sharepoint.com/:f:/g/personal/becakayu2aujung_waskita_co_id/EtKhMYsK2zBGvQMyfV2-WRsBC3ZCjB_RnOw0cJzRnU-lAg?e=ifnktz | AC56: https://ptwaskita-my.sharepoint.com/:f:/g/personal/becakayu2aujung_waskita_co_id/ElS0Je9n74BHv0P4RIjzSFcB3eCRaDiN4udpPNN6Swh4_A?e=FnrX4F | AD56: https://ptwaskita-my.sharepoint.com/:f:/g/personal/becakayu2aujung_waskita_co_id/ElS0Je9n74BHv0P4RIjzSFcB3eCRaDiN4udpPNN6Swh4_A?e=FnrX4F | AG56: =VLOOKUP(OfficeForms.Table[[#This Row],[Nama Proyek]],'Nama Proyek'!$D$2:$G$29,4,0) -> -6.4209386,107.1876008 | AK56: bb27975e-d5a0-4ded-9281-4fb93753765c
A57: 332 | B57: 44673 | C57: =B57 -> 44673 | D57: Esri_Anonymous | E57: Utomo Aryowibowo | F57: =E57 -> Utomo Aryowibowo | G57: Jalan Tol Cibitung - Cilincing Seksi 2 | I57: 0 | J57: 0 | K57: 0 | L57: 0 | M57: 0 | N57: 0 | O57: 0 | P57: 0 | Q57: 0 | R57: 0 | S57: 0 | T57: 0 | U57: 0 | V57: 0 | W57: 0 | X57: 0 | Y57: 0 | AA57: https://drive.google.com/file/d/1GTDsa7gWvHoKc8GaU6ozlozRG1z_DTe7/view?usp=sharing | AB57: https://drive.google.com/drive/folders/1oYy2XURVTfr70nYDGN_umbwAihwV2UIS?usp=sharing | AG57: =VLOOKUP(OfficeForms.Table[[#This Row],[Nama Proyek]],'Nama Proyek'!$D$2:$G$29,4,0) -> -6.13491053,106.93675986 | AK57: f7e99b11-652e-4f23-9193-3c9701b260b9
A58: 84 | B58: 44674 | C58: =B58 -> 44674 | D58: Esri_Anonymous | E58: Ganis Satria Pratama | F58: =E58 -> Ganis Satria Pratama | G58: Jalan Sofi - Wayabula 1 | H58: 44587 | I58: 49.27 | J58: 51.7 | K58: 1.09 | L58: 43.6 | M58: 0 | N58: 1.2 | O58: 0 | P58: 1.57 | Q58: 0 | R58: 0 | S58: 0 | T58: 0 | U58: 0 | V58: 0 | W58: 0 | X58: 0 | Y58: 0 | AG58: =VLOOKUP(OfficeForms.Table[[#This Row],[Nama Proyek]],'Nama Proyek'!$D$2:$G$29,4,0) -> 2.426249030,128.29766314 | AK58: 86a86e84-ca24-46a1-bbb1-887f33b192f1
A59: 86 | B59: 44674 | C59: =B59 -> 44674 | D59: Esri_Anonymous | E59: Ganis Satria Pratama | F59: =E59 -> Ganis Satria Pratama | G59: Jalan Sofi - Wayabula 1 | H59: 44615 | I59: 52.05 | J59: 54.9 | K59: 1.09 | L59: 47.18 | M59: 0 | N59: 0.54 | O59: 0 | P59: 1.57 | Q59: 0 | R59: 0 | S59: 0 | T59: 0 | U59: 0 | V59: 0 | W59: 0 | X59: 0 | Y59: 0 | AF59: Subkont blasting belum memulai pekerjaan (keterlambtan material) dan pengurusan ijin. | AG59: =VLOOKUP(OfficeForms.Table[[#This Row],[Nama Proyek]],'Nama Proyek'!$D$2:$G$29,4,0) -> 2.426249030,128.29766314 | AK59: 7cc50828-1ef7-4e31-bb04-4bce981390c4
A60: 89 | B60: 44674 | C60: =B60 -> 44674 | D60: Esri_Anonymous | E60: Ganis Satria Pratama | F60: =E60 -> Ganis Satria Pratama | G60: Jalan Sofi - Wayabula 1 | H60: 44645 | I60: 52.75 | J60: 59.93 | K60: 1.09 | L60: 47.83 | M60: 0 | N60: 0.54 | O60: 0 | P60: 1.62 | Q60: 0 | R60: 0 | S60: 0 | T60: 0 | U60: 0 | V60: 0 | W60: 0 | X60: 0 | Y60: 0 | AF60: Pekerja mogok kerja/pulang (sebagian belum dilunasi pembayarannya), akibatnya pekerjaan struktur terlambat | AG60: =VLOOKUP(OfficeForms.Table[[#This Row],[Nama Proyek]],'Nama Proyek'!$D$2:$G$29,4,0) -> 2.426249030,128.29766314 | AK60: 72e62bdc-8ece-4509-b669-a97b8a5eb463
A61: 97 | B61: 44674 | C61: =B61 -> 44674 | D61: Esri_Anonymous | E61: Ajik Prastiyo | F61: =E61 -> Ajik Prastiyo | G61: Jalan Tol Paspro Seksi 4 | H61: 44668 | I61: 20.2801 | J61: 40.1831 | K61: 0.12666629 | L61: 0.07636804 | M61: 8.6341195 | N61: 0.21776351 | O61: 0.01707589 | P61: 0.00311027 | Q61: 0.00061819 | R61: 0.20179342 | S61: 10.603495 | T61: 0 | U61: 0.08185856 | V61: 0 | W61: 0 | X61: 0.08712437 | Y61: 0 | AF61: Longsoran dibeberapa titik akses menuju lokasi proyek, akses terputus. | AG61: =VLOOKUP(OfficeForms.Table[[#This Row],[Nama Proyek]],'Nama Proyek'!$D$2:$G$29,4,0) -> -7.82225167,113.29968319 | AK61: 79d4021d-abfc-4381-84b6-82f91a8eedf9
A62: 87 | B62: 44674 | C62: =B62 -> 44674 | D62: Esri_Anonymous | E62: Ganis Satria Pratama | F62: =E62 -> Ganis Satria Pratama | G62: Jalan Sofi - Wayabula 1 | I62: 0 | J62: 0 | K62: 0 | L62: 0 | M62: 0 | N62: 0 | O62: 0 | P62: 0 | Q62: 0 | R62: 0 | S62: 0 | T62: 0 | U62: 0 | V62: 0 | W62: 0 | X62: 0 | Y62: 0 | AE62: 44774 | AG62: =VLOOKUP(OfficeForms.Table[[#This Row],[Nama Proyek]],'Nama Proyek'!$D$2:$G$29,4,0) -> 2.426249030,128.29766314 | AK62: 6039402e-4d22-46f2-91fe-4e2fdae0af0b
A63: 90 | B63: 44674 | C63: =B63 -> 44674 | D63: Esri_Anonymous | E63: Ganis Satria Pratama | F63: =E63 -> Ganis Satria Pratama | G63: Jalan Sofi - Wayabula 1 | I63: 0 | J63: 0 | K63: 0 | L63: 0 | M63: 0 | N63: 0 | O63: 0 | P63: 0 | Q63: 0 | R63: 0 | S63: 0 | T63: 0 | U63: 0 | V63: 0 | W63: 0 | X63: 0 | Y63: 0 | AE63: 44684 | AF63: Desain zona 1,2 dan 4 sudah final, namun desain zona 3 masih dilakukan pembahasan/asistensi perubahan trase serta dispensasi grade dengan Dirjen Bina Marga | AG63: =VLOOKUP(OfficeForms.Table[[#This Row],[Nama Proyek]],'Nama Proyek'!$D$2:$G$29,4,0) -> 2.426249030,128.29766314 | AK63: 70e1d164-2cf1-4a8b-ace7-2000db21590a
A64: 91 | B64: 44674 | C64: =B64 -> 44674 | D64: Esri_Anonymous | E64: Ganis Satria Pratama | F64: =E64 -> Ganis Satria Pratama | G64: Jalan Sofi - Wayabula 1 | I64: 0 | J64: 0 | K64: 0 | L64: 0 | M64: 0 | N64: 0 | O64: 0 | P64: 0 | Q64: 0 | R64: 0 | S64: 0 | T64: 0 | U64: 0 | V64: 0 | W64: 0 | X64: 0 | Y64: 0 | AE64: 44412 | AF64: PPK dan Pemerintah Kabupaten Pulau Morotai baru melakukan sosialisasi kepada warga desa cio maluleo, namun belum memberikan kejelasan terkait realisasi pembayaran 100% ganti rugi tanaman milik warga sehingga warga melakukan penutupan trase proyek dan men | AG64: =VLOOKUP(OfficeForms.Table[[#This Row],[Nama Proyek]],'Nama Proyek'!$D$2:$G$29,4,0) -> 2.426249030,128.29766314 | AK64: 3c6ea8a6-518d-4460-bc1a-056a07e183f6
A65: 92 | B65: 44674 | C65: =B65 -> 44674 | D65: Esri_Anonymous | E65: Ganis Satria Pratama | F65: =E65 -> Ganis Satria Pratama | G65: Jalan Sofi - Wayabula 1 | I65: 0 | J65: 0 | K65: 0 | L65: 0 | M65: 0 | N65: 0 | O65: 0 | P65: 0 | Q65: 0 | R65: 0 | S65: 0 | T65: 0 | U65: 0 | V65: 0 | W65: 0 | X65: 0 | Y65: 0 | AE65: 23/07/21 | AG65: =VLOOKUP(OfficeForms.Table[[#This Row],[Nama Proyek]],'Nama Proyek'!$D$2:$G$29,4,0) -> 2.426249030,128.29766314 | AK65: 7a235aa4-b31e-48ea-b446-96d7ad442a8a
A66: 94 | B66: 44674 | C66: =B66 -> 44674 | D66: Esri_Anonymous | E66: Ganis Satria Pratama | F66: =E66 -> Ganis Satria Pratama | G66: Jalan Sofi - Wayabula 1 | I66: 0 | J66: 0 | K66: 0 | L66: 0 | M66: 0 | N66: 0 | O66: 0 | P66: 0 | Q66: 0 | R66: 0 | S66: 0 | T66: 0 | U66: 0 | V66: 0 | W66: 0 | X66: 0 | Y66: 0 | AE66: 23/01/21 | AG66: =VLOOKUP(OfficeForms.Table[[#This Row],[Nama Proyek]],'Nama Proyek'!$D$2:$G$29,4,0) -> 2.426249030,128.29766314 | AK66: 1123fc0b-6f78-4bb8-bdbd-f356bacdf905
A67: 104 | B67: 44674 | C67: =B67 -> 44674 | D67: Esri_Anonymous | E67: Ajik Prastiyo | F67: =E67 -> Ajik Prastiyo | G67: Jalan Tol Paspro Seksi 4 | I67: 0 | J67: 0 | K67: 0 | L67: 0 | M67: 0 | N67: 0 | O67: 0 | P67: 0 | Q67: 0 | R67: 0 | S67: 0 | T67: 0 | U67: 0 | V67: 0 | W67: 0 | X67: 0 | Y67: 0 | AE67: 44564 | AG67: =VLOOKUP(OfficeForms.Table[[#This Row],[Nama Proyek]],'Nama Proyek'!$D$2:$G$29,4,0) -> -7.82225167,113.29968319 | AK67: 9132576e-5648-473a-a60f-3f9309ec3e0e
A68: 109 | B68: 44674 | C68: =B68 -> 44674 | D68: Esri_Anonymous | E68: Ajik Prastiyo | F68: =E68 -> Ajik Prastiyo | G68: Jalan Tol Paspro Seksi 4 | I68: 0 | J68: 0 | K68: 0 | L68: 0 | M68: 0 | N68: 0 | O68: 0 | P68: 0 | Q68: 0 | R68: 0 | S68: 0 | T68: 0 | U68: 0 | V68: 0 | W68: 0 | X68: 0 | Y68: 0 | AE68: 44564 | AF68: Pekerjaan Beton belum dapat memenuhi target harian pengecoran karena kekurangan stock material. | AG68: =VLOOKUP(OfficeForms.Table[[#This Row],[Nama Proyek]],'Nama Proyek'!$D$2:$G$29,4,0) -> -7.82225167,113.29968319 | AK68: 4c698679-9ad7-46b0-970e-ee02d8988724
A69: 110 | B69: 44674 | C69: =B69 -> 44674 | D69: Esri_Anonymous | E69: Ajik Prastiyo | F69: =E69 -> Ajik Prastiyo | G69: Jalan Tol Paspro Seksi 4 | I69: 0 | J69: 0 | K69: 0 | L69: 0 | M69: 0 | N69: 0 | O69: 0 | P69: 0 | Q69: 0 | R69: 0 | S69: 0 | T69: 0 | U69: 0 | V69: 0 | W69: 0 | X69: 0 | Y69: 0 | AE69: 44564 | AF69: Pekerjaan Besi Struktur masih kurang maksimal dikarenakan pengiriman material Besi D22, D25 dan D32 mengalami keterlambatan | AG69: =VLOOKUP(OfficeForms.Table[[#This Row],[Nama Proyek]],'Nama Proyek'!$D$2:$G$29,4,0) -> -7.82225167,113.29968319 | AK69: 97837e00-49f8-4638-a0c2-8ad604ea2375
A70: 111 | B70: 44674 | C70: =B70 -> 44674 | D70: Esri_Anonymous | E70: Ajik Prastiyo | F70: =E70 -> Ajik Prastiyo | G70: Jalan Tol Paspro Seksi 4 | I70: 0 | J70: 0 | K70: 0 | L70: 0 | M70: 0 | N70: 0 | O70: 0 | P70: 0 | Q70: 0 | R70: 0 | S70: 0 | T70: 0 | U70: 0 | V70: 0 | W70: 0 | X70: 0 | Y70: 0 | AE70: 44565 | AF70: Pekerjaan stressing Girder tertunda akibat WBP kehabisan stock Strand | AG70: =VLOOKUP(OfficeForms.Table[[#This Row],[Nama Proyek]],'Nama Proyek'!$D$2:$G$29,4,0) -> -7.82225167,113.29968319 | AK70: fa0408ec-9bf3-4d36-9b39-98802a069cd3
A71: 112 | B71: 44674 | C71: =B71 -> 44674 | D71: Esri_Anonymous | E71: Ajik Prastiyo | F71: =E71 -> Ajik Prastiyo | G71: Jalan Tol Paspro Seksi 4 | I71: 0 | J71: 0 | K71: 0 | L71: 0 | M71: 0 | N71: 0 | O71: 0 | P71: 0 | Q71: 0 | R71: 0 | S71: 0 | T71: 0 | U71: 0 | V71: 0 | W71: 0 | X71: 0 | Y71: 0 | AE71: 44565 | AF71: Penanganan Tanah Lunak oleh Owner pada Lokasi IC STA 00+000 – 01+000 dalam proses penunjukkan vendor oleh SCM | AG71: =VLOOKUP(OfficeForms.Table[[#This Row],[Nama Proyek]],'Nama Proyek'!$D$2:$G$29,4,0) -> -7.82225167,113.29968319 | AK71: aed3fea0-f304-4c7b-b20c-2cd76cd5ae2a
A72: 113 | B72: 44674 | C72: =B72 -> 44674 | D72: Esri_Anonymous | E72: Ajik Prastiyo | F72: =E72 -> Ajik Prastiyo | G72: Jalan Tol Paspro Seksi 4 | I72: 0 | J72: 0 | K72: 0 | L72: 0 | M72: 0 | N72: 0 | O72: 0 | P72: 0 | Q72: 0 | R72: 0 | S72: 0 | T72: 0 | U72: 0 | V72: 0 | W72: 0 | X72: 0 | Y72: 0 | AE72: 44563 | AF72: Perubahan desain, perhitungan volume tambah, dan item baru akibat Clearzone masih dalam proses. | AG72: =VLOOKUP(OfficeForms.Table[[#This Row],[Nama Proyek]],'Nama Proyek'!$D$2:$G$29,4,0) -> -7.82225167,113.29968319 | AK72: 20ffcf71-e4f5-4485-ac6c-478b32b77dff
A73: 114 | B73: 44674 | C73: =B73 -> 44674 | D73: Esri_Anonymous | E73: Ajik Prastiyo | F73: =E73 -> Ajik Prastiyo | G73: Jalan Tol Paspro Seksi 4 | I73: 0 | J73: 0 | K73: 0 | L73: 0 | M73: 0 | N73: 0 | O73: 0 | P73: 0 | Q73: 0 | R73: 0 | S73: 0 | T73: 0 | U73: 0 | V73: 0 | W73: 0 | X73: 0 | Y73: 0 | AE73: 44564 | AG73: =VLOOKUP(OfficeForms.Table[[#This Row],[Nama Proyek]],'Nama Proyek'!$D$2:$G$29,4,0) -> -7.82225167,113.29968319 | AK73: 84b69128-2a16-4f82-b3ca-c846dd3a7218
A74: 127 | B74: 44677 | C74: =B74 -> 44677 | D74: Esri_Anonymous | E74: Ajik Prastiyo | F74: =E74 -> Ajik Prastiyo | G74: Jalan Tol Paspro Seksi 4 | H74: 44528 | I74: 9.8632061 | J74: 15.807794 | K74: 0.05771719 | L74: 0.07636804 | M74: 4.4220249 | N74: 0.10412803 | O74: 0.00256716 | P74: 0.00209197 | Q74: 0.00061819 | R74: 0.10353709 | S74: 4.7592363 | T74: 0 | U74: 0.0537597 | V74: 0 | W74: 0 | X74: 0.0510575 | Y74: 0 | AF74: Ketersediaan PCU & PCI Girder untuk Erection masih belum mencukupi karena terkendala stressing girder yg belum siap | AG74: =VLOOKUP(OfficeForms.Table[[#This Row],[Nama Proyek]],'Nama Proyek'!$D$2:$G$29,4,0) -> -7.82225167,113.29968319 | AK74: 70ed3731-6b27-4f8c-8e87-30e383d42f85
A75: 125 | B75: 44677 | C75: =B75 -> 44677 | D75: Esri_Anonymous | E75: Ajik Prastiyo | F75: =E75 -> Ajik Prastiyo | G75: Jalan Tol Paspro Seksi 4 | H75: 44591 | I75: 14.614073 | J75: 23.753607 | K75: 0.09105705 | L75: 0.07636804 | M75: 6.0169144 | N75: 0.15711282 | O75: 0.01707589 | P75: 0.00209197 | Q75: 0.00061819 | R75: 0.10353709 | S75: 7.7819536 | T75: 0 | U75: 0.08185856 | V75: 0 | W75: 0 | X75: 0.05538523 | Y75: 0 | AG75: =VLOOKUP(OfficeForms.Table[[#This Row],[Nama Proyek]],'Nama Proyek'!$D$2:$G$29,4,0) -> -7.82225167,113.29968319 | AK75: fe8ae836-1fd5-4932-b35b-785b38353b04
A76: 126 | B76: 44677 | C76: =B76 -> 44677 | D76: Esri_Anonymous | E76: Ajik Prastiyo | F76: =E76 -> Ajik Prastiyo | G76: Jalan Tol Paspro Seksi 4 | H76: 44593 | I76: 12.888996 | J76: 20.244886 | K76: 0.0756807 | L76: 0.07636804 | M76: 5.393138 | N76: 0.14194267 | O76: 0.00256716 | P76: 0.00209197 | Q76: 0.00061819 | R76: 0.10353709 | S76: 6.7268071 | T76: 0 | U76: 0.08075999 | V76: 0 | W76: 0 | X76: 0.05538523 | Y76: 0 | AG76: =VLOOKUP(OfficeForms.Table[[#This Row],[Nama Proyek]],'Nama Proyek'!$D$2:$G$29,4,0) -> -7.82225167,113.29968319 | AK76: 989075db-03fe-4292-bb08-6eeb4ecc52cc
A77: 124 | B77: 44677 | C77: =B77 -> 44677 | D77: Esri_Anonymous | E77: Ajik Prastiyo | F77: =E77 -> Ajik Prastiyo | G77: Jalan Tol Paspro Seksi 4 | H77: 44619 | I77: 15.987054 | J77: 28.700824 | K77: 0.09325839 | L77: 0.07636804 | M77: 6.4965875 | N77: 0.17004126 | O77: 0.01707589 | P77: 0.00209197 | Q77: 0.00061819 | R77: 0.10685451 | S77: 8.6250756 | T77: 0 | U77: 0.08185856 | V77: 0 | W77: 0 | X77: 0.08712437 | Y77: 0 | AG77: =VLOOKUP(OfficeForms.Table[[#This Row],[Nama Proyek]],'Nama Proyek'!$D$2:$G$29,4,0) -> -7.82225167,113.29968319 | AK77: 79038291-62b3-4f30-bc58-ef2d515848c9
A78: 131 | B78: 44677 | C78: =B78 -> 44677 | D78: Esri_Anonymous | E78: Haryo Widiandoko | F78: =E78 -> Haryo Widiandoko | G78: Jalan Tol Japek II Selatan Paket 3 | H78: 44621 | I78: 65.668 | J78: 66.17 | K78: 0.141 | L78: 0.161 | M78: 19.269 | N78: 2.165 | O78: 1.952 | P78: 0.066 | Q78: 0.587 | R78: 7.766 | S78: 32.266 | T78: 0.239 | U78: 0.56 | V78: 0.039 | W78: 0 | X78: 0.905 | Y78: 0 | AG78: =VLOOKUP(OfficeForms.Table[[#This Row],[Nama Proyek]],'Nama Proyek'!$D$2:$G$29,4,0) -> -6.42873464,107.19897003 | AK78: 23ed115b-f4c0-47b1-b7e5-a9685e2fac9f
A79: 123 | B79: 44677 | C79: =B79 -> 44677 | D79: Esri_Anonymous | E79: Ajik Prastiyo | F79: =E79 -> Ajik Prastiyo | G79: Jalan Tol Paspro Seksi 4 | H79: 44647 | I79: 18.008816 | J79: 35.555542 | K79: 0.09325839 | L79: 0.07636804 | M79: 7.4859981 | N79: 0.18931913 | O79: 0.01707589 | P79: 0.00311027 | Q79: 0.00061819 | R79: 0.20179342 | S79: 9.5421916 | T79: 0 | U79: 0.08185856 | V79: 0 | W79: 0 | X79: 0.08712437 | Y79: 0 | AG79: =VLOOKUP(OfficeForms.Table[[#This Row],[Nama Proyek]],'Nama Proyek'!$D$2:$G$29,4,0) -> -7.82225167,113.29968319 | AK79: 610f44e6-8fd6-44f0-856b-285e4249f14c
A80: 85 | B80: 44677 | C80: =B80 -> 44677 | D80: Esri_Anonymous | E80: BUDI SUGORO | F80: =E80 -> BUDI SUGORO | G80: Fly Over Simpang Sekip - Palembang (JOI 65%) | H80: 44674 | I80: 22.81 | J80: 23 | K80: 0 | L80: 21.414 | M80: 0 | N80: 0 | O80: 0 | P80: 0 | Q80: 0 | R80: 0.231 | S80: 0 | T80: 0 | U80: 0 | V80: 0 | W80: 0 | X80: 0 | Y80: 0 | AG80: =VLOOKUP(OfficeForms.Table[[#This Row],[Nama Proyek]],'Nama Proyek'!$D$2:$G$29,4,0) -> -2.95293103,104.75455094 | AK80: 33bcb9ff-2636-46a2-8f33-232ba56609fb
A81: 163 | B81: 44677 | C81: =B81 -> 44677 | D81: Esri_Anonymous | E81: Utomo Aryowibowo | F81: =E81 -> Utomo Aryowibowo | G81: Jalan Tol Cibitung - Cilincing Seksi 2 | H81: 44679 | I81: 83.908 | J81: 84.869 | K81: 0 | L81: -0.001 | M81: 0.152 | N81: 0.236 | O81: 0 | P81: 0 | Q81: 0 | R81: 1.801 | S81: 64.892 | T81: 0 | U81: 0.23 | V81: 0.317 | W81: 0 | X81: 0.518 | Y81: 0 | AG81: =VLOOKUP(OfficeForms.Table[[#This Row],[Nama Proyek]],'Nama Proyek'!$D$2:$G$29,4,0) -> -6.13491053,106.93675986 | AK81: 60d714c8-2a7f-4783-a76c-1fc7d99e322b
A82: 57 | B82: 44677 | C82: =B82 -> 44677 | D82: Esri_Anonymous | E82: Nizar Zulkarnain | F82: =E82 -> Nizar Zulkarnain | G82: Jalan Tol Cimanggis Cibitung Seksi 2 | I82: 0 | J82: 0 | K82: 0 | L82: 0 | M82: 0 | N82: 0 | O82: 0 | P82: 0 | Q82: 0 | R82: 0 | S82: 0 | T82: 0 | U82: 0 | V82: 0 | W82: 0 | X82: 0 | Y82: 0 | AC82: https://ptwaskita-my.sharepoint.com/personal/nizar_zulkarnain_waskita_co_id/_layouts/15/onedrive.aspx?id=%2Fpersonal%2Fnizar%5Fzulkarnain%5Fwaskita%5Fco%5Fid%2FDocuments%2FOrthophoto | AG82: =VLOOKUP(OfficeForms.Table[[#This Row],[Nama Proyek]],'Nama Proyek'!$D$2:$G$29,4,0) -> -6.35008011,107.02324233 | AK82: e2596b29-a78e-4565-b330-3796250c14e2
A83: 59 | B83: 44677 | C83: =B83 -> 44677 | D83: Esri_Anonymous | E83: Nizar Zulkarnain | F83: =E83 -> Nizar Zulkarnain | G83: Jalan Tol Cimanggis Cibitung Seksi 2 | I83: 0 | J83: 0 | K83: 0 | L83: 0 | M83: 0 | N83: 0 | O83: 0 | P83: 0 | Q83: 0 | R83: 0 | S83: 0 | T83: 0 | U83: 0 | V83: 0 | W83: 0 | X83: 0 | Y83: 0 | AC83: https://ptwaskita-my.sharepoint.com/:f:/g/personal/nizar_zulkarnain_waskita_co_id/EqnPyDu26RxIisn3JPE4K6gBUTZWwUtFrihgA0LqhtrjzA?e=kq5cWW | AF83: 1. Pekerjaan Tanah Borrow Material Target Februari 35.000 m3 saat ini belum dilaksanakan pekerjaan Borrow (Percepatan administrasi untuk berkontrak dengan vendor baru, serta koordinasi dengan pihak eksternal terkait ijin Quarry) 2. Pekerjaan Struktur WSBP saat ini dalam proses persiapan lahan untuk pendirian Baching Plan, Rencana M2 Maret mulai beroprasi. 3. Legal dan Administrasi Pihak JPB dan KSO telah bersurat mengenai keterlambatan di zona Waskita dan akan dilakukan skema pengelolaan vendor bersama atau pengambil alihan pekerjaan oleh KSO Telah dilaksanakan SCM tahap 1 dan akan dilanjutkan dengan SCM tahap 2 (Berkoordinasi dengan UB terkait sumber daya yang harus dipenuhi untuk mencapai target test case | AG83: =VLOOKUP(OfficeForms.Table[[#This Row],[Nama Proyek]],'Nama Proyek'!$D$2:$G$29,4,0) -> -6.35008011,107.02324233 | AK83: 9305f542-e5be-4ce8-bdd3-abd27a36ff67
A84: 98 | B84: 44677 | C84: =B84 -> 44677 | D84: Esri_Anonymous | E84: ADITYA ANGGA | F84: =E84 -> ADITYA ANGGA | G84: Fly Over Simpang Sekip - Palembang (JOI 65%) | I84: 0 | J84: 0 | K84: 0 | L84: 0 | M84: 0 | N84: 0 | O84: 0 | P84: 0 | Q84: 0 | R84: 0 | S84: 0 | T84: 0 | U84: 0 | V84: 0 | W84: 0 | X84: 0 | Y84: 0 | AE84: 44899 | AG84: =VLOOKUP(OfficeForms.Table[[#This Row],[Nama Proyek]],'Nama Proyek'!$D$2:$G$29,4,0) -> -2.95293103,104.75455094 | AK84: a66f42ab-592f-4641-8c4f-21a0e6fe56b5
A85: 116 | B85: 44677 | C85: =B85 -> 44677 | D85: Esri_Anonymous | E85: ISNAEN DWI SANJOYO | F85: =E85 -> ISNAEN DWI SANJOYO | G85: Jalan Tol Becakayu 2A Ujung | I85: 0 | J85: 0 | K85: 0 | L85: 0 | M85: 0 | N85: 0 | O85: 0 | P85: 0 | Q85: 0 | R85: 0 | S85: 0 | T85: 0 | U85: 0 | V85: 0 | W85: 0 | X85: 0 | Y85: 0 | AE85: 44563 | AG85: =VLOOKUP(OfficeForms.Table[[#This Row],[Nama Proyek]],'Nama Proyek'!$D$2:$G$29,4,0) -> -6.4209386,107.1876008 | AK85: ce7a77d1-bef2-491c-bafd-40f376085fb1
A86: 134 | B86: 44677 | C86: =B86 -> 44677 | D86: Esri_Anonymous | E86: BASUKI RAHMAT HAKIM | F86: =E86 -> BASUKI RAHMAT HAKIM | G86: Jalan Long Semamu - Long Bawan 2 (JOP 70%) | I86: 0 | J86: 0 | K86: 0 | L86: 0 | M86: 0 | N86: 0 | O86: 0 | P86: 0 | Q86: 0 | R86: 0 | S86: 0 | T86: 0 | U86: 0 | V86: 0 | W86: 0 | X86: 0 | Y86: 0 | AE86: 14/04/22 | AF86: Perlu pengalihan trase tambahan untuk mengejar panjang efektif dan penyesuaian terhadap volume kontrak karena trase alternatif secara panjang desainnya lebih kecil dan lebih pendek. | AG86: =VLOOKUP(OfficeForms.Table[[#This Row],[Nama Proyek]],'Nama Proyek'!$D$2:$G$29,4,0) -> 3.76047575,115.89977678 | AK86: 1e300e4b-3710-42dd-8e4b-1a6bc9f6a78c
A87: 135 | B87: 44677 | C87: =B87 -> 44677 | D87: Esri_Anonymous | E87: Aji Kukuh Pambudi | F87: Aji Kukuh Pambudi | G87: Fly Over Simpang Sekip - Palembang (JOI 65%) | I87: 0 | J87: 0 | K87: 0 | L87: 0 | M87: 0 | N87: 0 | O87: 0 | P87: 0 | Q87: 0 | R87: 0 | S87: 0 | T87: 0 | U87: 0 | V87: 0 | W87: 0 | X87: 0 | Y87: 0 | AE87: 15/04/22 | AF87: Terdapat perbedaan elevasi yang sangat signifikan (50 – 190 meter) antara Eksisting DED dan Eksisting Aktual Lapangan (Sta. 12+800 s/d 20+000). Pada Sta. 20+000 – 28+000 apabila mengikuti CL DED terdapat selisih over volume dikarenakan perbedaan eksi | AG87: =VLOOKUP(OfficeForms.Table[[#This Row],[Nama Proyek]],'Nama Proyek'!$D$2:$G$29,4,0) -> -2.95293103,104.75455094 | AK87: 7f077173-509a-4b84-96fa-f96c42004ae1
A88: 136 | B88: 44677 | C88: =B88 -> 44677 | D88: Esri_Anonymous | E88: Aji Kukuh Pambudi | F88: Aji Kukuh Pambudi | G88: Fly Over Simpang Sekip - Palembang (JOI 65%) | I88: 0 | J88: 0 | K88: 0 | L88: 0 | M88: 0 | N88: 0 | O88: 0 | P88: 0 | Q88: 0 | R88: 0 | S88: 0 | T88: 0 | U88: 0 | V88: 0 | W88: 0 | X88: 0 | Y88: 0 | AE88: 15/04/22 | AG88: =VLOOKUP(OfficeForms.Table[[#This Row],[Nama Proyek]],'Nama Proyek'!$D$2:$G$29,4,0) -> -2.95293103,104.75455094 | AK88: d88d9398-9035-47aa-9fb7-ac8323cfb309
A89: 137 | B89: 44677 | C89: =B89 -> 44677 | D89: Esri_Anonymous | E89: BASUKI RAHMAT HAKIM | F89: =E89 -> BASUKI RAHMAT HAKIM | G89: Jalan Long Semamu - Long Bawan 2 (JOP 70%) | I89: 0 | J89: 0 | K89: 0 | L89: 0 | M89: 0 | N89: 0 | O89: 0 | P89: 0 | Q89: 0 | R89: 0 | S89: 0 | T89: 0 | U89: 0 | V89: 0 | W89: 0 | X89: 0 | Y89: 0 | AA89: https://drive.google.com/file/d/1W8D1rsMJ-lydyMUMby8lo4uV7tULB-ZQ/view?usp=sharing | AB89: https://drive.google.com/drive/folders/1cndGMPpQPHboXGpybVs9dmp6VUJm6Lzf?usp=sharing | AC89: https://ptwaskita-my.sharepoint.com/:i:/g/personal/ahmadi_ahmadi_waskita_co_id/EUkDiOPm-aVKiUq8FkYuSDUBWzJKgXZKASp4SAmYnvAKAg?e=69KZfQ | AD89: https://ptwaskita-my.sharepoint.com/:u:/g/personal/ahmadi_ahmadi_waskita_co_id/EXBq3_GyagNHjZD3WAET7kUB-30AXHCgm2JFcqDSpkI0CA?e=0QWj5p | AG89: =VLOOKUP(OfficeForms.Table[[#This Row],[Nama Proyek]],'Nama Proyek'!$D$2:$G$29,4,0) -> 3.76047575,115.89977678 | AK89: 2ca306ac-0d6b-4654-b9b9-f4c896b2333b
A90: 366 | B90: 44677 | C90: =B90 -> 44677 | D90: Esri_Anonymous | E90: Haryo Widiandoko | F90: =E90 -> Haryo Widiandoko | G90: Jalan Tol Japek II Selatan Paket 3 | I90: 0 | J90: 0 | K90: 0 | L90: 0 | M90: 0 | N90: 0 | O90: 0 | P90: 0 | Q90: 0 | R90: 0 | S90: 0 | T90: 0 | U90: 0 | V90: 0 | W90: 0 | X90: 0 | Y90: 0 | AE90: 44564 | AG90: =VLOOKUP(OfficeForms.Table[[#This Row],[Nama Proyek]],'Nama Proyek'!$D$2:$G$29,4,0) -> -6.42873464,107.19897003 | AK90: 9ff9dc32-177a-4014-a204-133b4ef50cec
A91: 388 | B91: 44677 | C91: =B91 -> 44677 | D91: Esri_Anonymous | E91: Haryo Widiandoko | F91: =E91 -> Haryo Widiandoko | G91: Jalan Tol Japek II Selatan Paket 3 | I91: 0 | J91: 0 | K91: 0 | L91: 0 | M91: 0 | N91: 0 | O91: 0 | P91: 0 | Q91: 0 | R91: 0 | S91: 0 | T91: 0 | U91: 0 | V91: 0 | W91: 0 | X91: 0 | Y91: 0 | AE91: 44564 | AG91: =VLOOKUP(OfficeForms.Table[[#This Row],[Nama Proyek]],'Nama Proyek'!$D$2:$G$29,4,0) -> -6.42873464,107.19897003 | AK91: 13bc87da-0297-488e-960d-3b018568383e
A92: 390 | B92: 44677 | C92: =B92 -> 44677 | D92: Esri_Anonymous | E92: Haryo Widiandoko | F92: =E92 -> Haryo Widiandoko | G92: Jalan Tol Japek II Selatan Paket 3 | I92: 0 | J92: 0 | K92: 0 | L92: 0 | M92: 0 | N92: 0 | O92: 0 | P92: 0 | Q92: 0 | R92: 0 | S92: 0 | T92: 0 | U92: 0 | V92: 0 | W92: 0 | X92: 0 | Y92: 0 | AE92: 27/04/22 | AF92: Keterlambatan alat bored pile menyebabkan start drilling terlambat 2 bulan | AG92: =VLOOKUP(OfficeForms.Table[[#This Row],[Nama Proyek]],'Nama Proyek'!$D$2:$G$29,4,0) -> -6.42873464,107.19897003 | AK92: 302540a0-ed86-469e-8524-45867183ae68
A93: 394 | B93: 44677 | C93: =B93 -> 44677 | D93: Esri_Anonymous | E93: Haryo Widiandoko | F93: =E93 -> Haryo Widiandoko | G93: Jalan Tol Japek II Selatan Paket 3 | I93: 0 | J93: 0 | K93: 0 | L93: 0 | M93: 0 | N93: 0 | O93: 0 | P93: 0 | Q93: 0 | R93: 0 | S93: 0 | T93: 0 | U93: 0 | V93: 0 | W93: 0 | X93: 0 | Y93: 0 | AE93: 27/04/22 | AF93: 1. Pekerjaan Tanah Cuaca hujan dengan insentitas sering subkon masih banyak belum berproduksi 2. Pekerjaan Beton WBP harus mendirikan Plan di Sta Awal (kecil) | AG93: =VLOOKUP(OfficeForms.Table[[#This Row],[Nama Proyek]],'Nama Proyek'!$D$2:$G$29,4,0) -> -6.42873464,107.19897003 | AK93: 21b463a9-3413-45b5-a7cd-3917c1452e53
A94: 395 | B94: 44677 | C94: =B94 -> 44677 | D94: Esri_Anonymous | E94: Haryo Widiandoko | F94: =E94 -> Haryo Widiandoko | G94: Jalan Tol Japek II Selatan Paket 3 | I94: 0 | J94: 0 | K94: 0 | L94: 0 | M94: 0 | N94: 0 | O94: 0 | P94: 0 | Q94: 0 | R94: 0 | S94: 0 | T94: 0 | U94: 0 | V94: 0 | W94: 0 | X94: 0 | Y94: 0 | AE94: 27/04/22 | AG94: =VLOOKUP(OfficeForms.Table[[#This Row],[Nama Proyek]],'Nama Proyek'!$D$2:$G$29,4,0) -> -6.42873464,107.19897003 | AK94: 1e839d59-cf06-45d0-9d30-896fb018527d
A95: 397 | B95: 44677 | C95: =B95 -> 44677 | D95: Esri_Anonymous | E95: Haryo Widiandoko | F95: =E95 -> Haryo Widiandoko | G95: Jalan Tol Japek II Selatan Paket 3 | I95: 0 | J95: 0 | K95: 0 | L95: 0 | M95: 0 | N95: 0 | O95: 0 | P95: 0 | Q95: 0 | R95: 0 | S95: 0 | T95: 0 | U95: 0 | V95: 0 | W95: 0 | X95: 0 | Y95: 0 | AE95: 27/04/22 | AG95: =VLOOKUP(OfficeForms.Table[[#This Row],[Nama Proyek]],'Nama Proyek'!$D$2:$G$29,4,0) -> -6.42873464,107.19897003 | AK95: e688a102-01b9-4e09-ae52-8b47ece49ec6
A96: 410 | B96: 44677 | C96: =B96 -> 44677 | D96: Esri_Anonymous | E96: Haryo Widiandoko | F96: =E96 -> Haryo Widiandoko | G96: Jalan Tol Japek II Selatan Paket 3 | I96: 0 | J96: 0 | K96: 0 | L96: 0 | M96: 0 | N96: 0 | O96: 0 | P96: 0 | Q96: 0 | R96: 0 | S96: 0 | T96: 0 | U96: 0 | V96: 0 | W96: 0 | X96: 0 | Y96: 0 | AB96: https://drive.google.com/drive/folders/1HK4DSjLm97leXnZWUfZQEwSYbdhGVzN5 | AF96: 1. Proses perubahan Cara Pembayaran semula Turn Key Modified 3 kali pembayaran : Pembayaran Pendahuluan 5%, PHO Gate to Gate Sadang-Kutanegara, PHO Keseluruhan. menjadi Turnkey Modified 5 kali pembayaran : Pendahuluan 5%, 70% Gate to Gate Sadang- Kutaneg | AG96: =VLOOKUP(OfficeForms.Table[[#This Row],[Nama Proyek]],'Nama Proyek'!$D$2:$G$29,4,0) -> -6.42873464,107.19897003 | AK96: adfcc41e-33eb-4247-809e-1ebdac30e160
A97: 434 | B97: 44677 | C97: =B97 -> 44677 | D97: Esri_Anonymous | E97: Utomo Aryowibowo | F97: =E97 -> Utomo Aryowibowo | G97: Jalan Tol Cibitung - Cilincing Seksi 2 | I97: 0 | J97: 0 | K97: 0 | L97: 0 | M97: 0 | N97: 0 | O97: 0 | P97: 0 | Q97: 0 | R97: 0 | S97: 0 | T97: 0 | U97: 0 | V97: 0 | W97: 0 | X97: 0 | Y97: 0 | AE97: 26/04/22 | AF97: Main Road Zona 2 sudah ada +- 70 Pilehead siap erection Full Slab namun tekendala material full slab yang belum ada (keb. +- 840 Pcs) | AG97: =VLOOKUP(OfficeForms.Table[[#This Row],[Nama Proyek]],'Nama Proyek'!$D$2:$G$29,4,0) -> -6.13491053,106.93675986 | AK97: bf6351db-7f29-40f2-8334-adca60a32ef9
A98: 435 | B98: 44677 | C98: =B98 -> 44677 | D98: Esri_Anonymous | E98: Utomo Aryowibowo | F98: =E98 -> Utomo Aryowibowo | G98: Jalan Tol Cibitung - Cilincing Seksi 2 | I98: 0 | J98: 0 | K98: 0 | L98: 0 | M98: 0 | N98: 0 | O98: 0 | P98: 0 | Q98: 0 | R98: 0 | S98: 0 | T98: 0 | U98: 0 | V98: 0 | W98: 0 | X98: 0 | Y98: 0 | AE98: 26/04/22 | AG98: =VLOOKUP(OfficeForms.Table[[#This Row],[Nama Proyek]],'Nama Proyek'!$D$2:$G$29,4,0) -> -6.13491053,106.93675986 | AK98: e799e720-fff2-499b-ae66-113c901c33ad
A99: 449 | B99: 44677 | C99: =B99 -> 44677 | D99: Esri_Anonymous | E99: Utomo Aryowibowo | F99: =E99 -> Utomo Aryowibowo | G99: Jalan Tol Cibitung - Cilincing Seksi 2 | I99: 0 | J99: 0 | K99: 0 | L99: 0 | M99: 0 | N99: 0 | O99: 0 | P99: 0 | Q99: 0 | R99: 0 | S99: 0 | T99: 0 | U99: 0 | V99: 0 | W99: 0 | X99: 0 | Y99: 0 | AE99: 26/04/22 | AF99: P3 BKT sedang proses pekerjaan metode cofferdam, pemacanganan SSP | AG99: =VLOOKUP(OfficeForms.Table[[#This Row],[Nama Proyek]],'Nama Proyek'!$D$2:$G$29,4,0) -> -6.13491053,106.93675986 | AK99: 1225c96d-53d8-471a-a6f5-111adab71b3f
A100: 450 | B100: 44677 | C100: =B100 -> 44677 | D100: Esri_Anonymous | E100: Utomo Aryowibowo | F100: =E100 -> Utomo Aryowibowo | G100: Jalan Tol Cibitung - Cilincing Seksi 2 | I100: 0 | J100: 0 | K100: 0 | L100: 0 | M100: 0 | N100: 0 | O100: 0 | P100: 0 | Q100: 0 | R100: 0 | S100: 0 | T100: 0 | U100: 0 | V100: 0 | W100: 0 | X100: 0 | Y100: 0 | AE100: 26/04/22 | AF100: 1. Keterlambatan pengiriman BBM ke area proyek akibat kondisi akses 2. Pengiriman sparepart perbaikan alat terlambat akibat terbatasnya jasa pengiriman barang ke arah proyek | AG100: =VLOOKUP(OfficeForms.Table[[#This Row],[Nama Proyek]],'Nama Proyek'!$D$2:$G$29,4,0) -> -6.13491053,106.93675986 | AK100: edf0877b-19cd-4d93-b398-029bcb6356ef
...

Sheet Progress Test
A1: Nama Proyek | B1: Periode | C1: Rencana | D1: Realisasi
A2: Fly Over Simpang Sekip - Palembang (JOI 65%) | C2: 0 | D2: 0
A3: Fly Over Simpang Sekip - Palembang (JOI 65%) | C3: 0 | D3: 0
A4: Fly Over Simpang Sekip - Palembang (JOI 65%) | C4: 0 | D4: 0
A5: Fly Over Simpang Sekip - Palembang (JOI 65%) | C5: 0 | D5: 0
A6: Fly Over Simpang Sekip - Palembang (JOI 65%) | C6: 0 | D6: 0
A7: Fly Over Simpang Sekip - Palembang (JOI 65%) | C7: 0 | D7: 0
A8: Fly Over Simpang Sekip - Palembang (JOI 65%) | C8: 0 | D8: 0
A9: Fly Over Simpang Sekip - Palembang (JOI 65%) | C9: 0 | D9: 0
A10: Fly Over Simpang Sekip - Palembang (JOI 65%) | C10: 0 | D10: 0
A11: Fly Over Simpang Sekip - Palembang (JOI 65%) | C11: 0 | D11: 0
A12: Fly Over Simpang Sekip - Palembang (JOI 65%) | C12: 0 | D12: 0
A13: Fly Over Simpang Sekip - Palembang (JOI 65%) | C13: 0 | D13: 0
... A16: Fly Over Simpang Sekip - Palembang (JOI 65%) | C16: 0 | D16: 0
A17: Jalan Akses Bandara VVIP IKN (JOI 35%) | B17: 45657 | C17: 91.486 | D17: 91.365
A18: Jalan Baru Kretek Girijati (JOI Leader 52.5%) | B18: 45651 | C18: 70.961 | D18: 57.712
A19: Jalan Baru Kretek Girijati (JOI Leader 52.5%) | B19: 45682 | C19: 74.049 | D19: 60.862
A20: Jalan Baru Kretek Girijati (JOI Leader 52.5%) | B20: 45713 | C20: 76.06 | D20: 63.319
A21: Jalan Baru Kretek Girijati (JOI Leader 52.5%) | B21: 45772 | C21: 82.018 | D21: 71.509
A22: Jalan Baru Kretek Girijati (JOI Leader 52.5%) | B22: 45802 | C22: 84.648 | D22: 77.971
A23: Jalan Baru Kretek Girijati (JOI Leader 52.5%) | B23: 45863 | C23: 91.538 | D23: 91.448
A24: Jalan Baru Kretek Girijati (JOI Leader 52.5%) | B24: 45894 | C24: 94.02 | D24: 89.63
A25: Jalan Baru Kretek Girijati (JOI Leader 52.5%) | B25: 45925 | C25: 95.486 | D25: 91.969
A26: Jalan Baru Kretek Girijati (JOI Leader 52.5%) | C26: 0 | D26: 0
A27: Jalan Baru Kretek Girijati (JOI Leader 52.5%) | C27: 0 | D27: 0
A28: Jalan Baru Kretek Girijati (JOI Leader 52.5%) | C28: 0 | D28: 0
A29: Jalan Baru Kretek Girijati (JOI Leader 52.5%) | C29: 0 | D29: 0
A30: Jalan Baru Kretek Girijati (JOI Leader 52.5%) | B30: 45956 | C30: 89.868 | D30: 80.591
A31: Jalan dan Jembatan Bts. Blitar Lot 6B | B31: 44833 | C31: 31.972 | D31: 19.758
A32: Jalan dan Jembatan Bts. Blitar Lot 6B | B32: 44862 | C32: 39.934 | D32: 32.395
A33: Jalan dan Jembatan Bts. Blitar Lot 6B | B33: 44887 | C33: 44.435 | D33: 41.701
A34: Jalan dan Jembatan Bts. Blitar Lot 6B | B34: 44893 | C34: 46.983 | D34: 44.803
A35: Jalan dan Jembatan Bts. Blitar Lot 6B | B35: 44925 | C35: 47.71 | D35: 60.675
A36: Jalan dan Jembatan Bts. Blitar Lot 6B | B36: 44956 | C36: 48.587 | D36: 80.031
A37: Jalan dan Jembatan Bts. Blitar Lot 6B | B37: 44959 | C37: 48.587 | D37: 57.69
A38: Jalan dan Jembatan Bts. Blitar Lot 6B | B38: 45012 | C38: 52.673 | D38: 95.427
A39: Jalan Distrik (Feeder) IKN (JOI 50%) | B39: 45653 | C39: 100 | D39: 100
A40: Jalan Distrik (Feeder) IKN (JOI 50%) | B40: 44967 | C40: 5.626 | D40: 5.798
A41: Jalan Distrik (Feeder) IKN (JOI 50%) | C41: 0 | D41: 0
A42: Jalan Distrik (Feeder) IKN (JOI 50%) | C42: 0 | D42: 0
A43: Jalan IKN Lingkar Sepaku Segmen 4 | C43: 0 | D43: 0
A44: Jalan IKN Lingkar Sepaku Segmen 4 | C44: 0 | D44: 0
A45: Jalan IKN Lingkar Sepaku Segmen 4 | C45: 0 | D45: 0
A46: Jalan IKN Lingkar Sepaku Segmen 4 | C46: 0 | D46: 0
A47: Jalan IKN Lingkar Sepaku Segmen 4 | B47: 44885 | C47: 3.904 | D47: 6.54
A48: Jalan IKN Lingkar Sepaku Segmen 4 | B48: 44890 | C48: 4.17 | D48: 7.912
A49: Jalan IKN Lingkar Sepaku Segmen 4 | B49: 44920 | C49: 11.744 | D49: 8.945
A50: Jalan IKN Lingkar Sepaku Segmen 4 | B50: 44948 | C50: 13.318 | D50: 12.861
A51: Jalan IKN Lingkar Sepaku Segmen 4 | B51: 44951 | C51: 13.933 | D51: 12.861
A52: Jalan IKN Lingkar Sepaku Segmen 4 | B52: 44961 | C52: 14.085 | D52: 14.847
A53: Jalan IKN Lingkar Sepaku Segmen 4 | B53: 44976 | C53: 14.458 | D53: 17.092
A54: Jalan IKN Lingkar Sepaku Segmen 4 | B54: 45004 | C54: 18.03 | D54: 20.707
A55: Jalan IKN Lingkar Sepaku Segmen 4 | B55: 45041 | C55: 21.179 | D55: 25.369
A56: Jalan IKN Lingkar Sepaku Segmen 4 | B56: 45067 | C56: 24.55 | D56: 31.361
A57: Jalan IKN Lingkar Sepaku Segmen 4 | B57: 45092 | C57: 36.607 | D57: 40.282
A58: Jalan IKN Lingkar Sepaku Segmen 4 | B58: 45130 | C58: 47.175 | D58: 44.727
... A64: Jalan Long Semamu - Long Bawan 2 (JOP 70%) | B64: 45133 | C64: 58.57 | D64: 64.64
A65: Jalan Long Semamu - Long Bawan 2 (JOP 70%) | C65: 0 | D65: 0
A66: Jalan Long Semamu - Long Bawan 2 (JOP 70%) | C66: 0 | D66: 0
A67: Jalan Long Semamu - Long Bawan 2 (JOP 70%) | C67: 0 | D67: 0
A68: Jalan Long Semamu - Long Bawan 2 (JOP 70%) | B68: 45190 | C68: 80.41 | D68: 84.72
A69: Jalan Long Semamu - Long Bawan 2 (JOP 70%) | C69: 0 | D69: 0
A70: Jalan Long Semamu - Long Bawan 2 (JOP 70%) | C70: 0 | D70: 0
A71: Jalan Long Semamu - Long Bawan 2 (JOP 70%) | C71: 0 | D71: 0
A72: Jalan Long Semamu - Long Bawan 2 (JOP 70%) | B72: 45224 | C72: 91.9 | D72: 96
A73: Jalan Lot 2 Buluwalang-Sidomulyo-Tambakrejo (JOI 40%) | B73: 45653 | C73: 66.919 | D73: 25.334
A74: Jalan Lot 2 Buluwalang-Sidomulyo-Tambakrejo (JOI 40%) | B74: 45687 | C74: 69.86 | D74: 31.545
A75: Jalan Lot 2 Buluwalang-Sidomulyo-Tambakrejo (JOI 40%) | B75: 45715 | C75: 72.505 | D75: 35.937
A76: Jalan Lot 2 Buluwalang-Sidomulyo-Tambakrejo (JOI 40%) | B76: 45771 | C76: 75.66 | D76: 44.918
A77: Jalan Lot 2 Buluwalang-Sidomulyo-Tambakrejo (JOI 40%) | B77: 45799 | C77: 83.241 | D77: 48.986
A78: Jalan Lot 2 Buluwalang-Sidomulyo-Tambakrejo (JOI 40%) | B78: 45834 | C78: 83.279 | D78: 54.394
A79: Jalan Lot 2 Buluwalang-Sidomulyo-Tambakrejo (JOI 40%) | B79: 45862 | C79: 83.685 | D79: 59.3
A80: Jalan Lot 2 Buluwalang-Sidomulyo-Tambakrejo (JOI 40%) | B80: 45890 | C80: 85.078 | D80: 64.077
A81: Jalan Lot 2 Buluwalang-Sidomulyo-Tambakrejo (JOI 40%) | B81: 45925 | C81: 90.646 | D81: 69.82
A82: Jalan Lot 2 Buluwalang-Sidomulyo-Tambakrejo (JOI 40%) | B82: 45960 | C82: 94.948 | D82: 75.667
A83: Jalan Seksi 6C-1 KIPP IKN (JOI 32.50%) | B83: 0 | C83: 100 | D83: 94.823
... A93: Jalan Tol Akses Patimban Paket 2 (JOI 60%) | B93: 45956 | C93: 58.868 | D93: 93.394
A94: Jalan Tol Bayunglencir - Tempino Seksi 1 (JOI 40%) | C94: 0 | D94: 0
A95: Jalan Tol Bayunglencir - Tempino Seksi 1 (JOI 40%) | C95: 0 | D95: 0
A96: Jalan Tol Bayunglencir - Tempino Seksi 1 (JOI 40%) | B96: 45132 | C96: 2.345 | D96: 2.263
A97: Jalan Tol Bayunglencir - Tempino Seksi 1 (JOI 40%) | C97: 0 | D97: 0
A98: Jalan Tol Bayunglencir - Tempino Seksi 1 (JOI 40%) | B98: 45163 | C98: 6.502 | D98: 6.298
A99: Jalan Tol Bayunglencir - Tempino Seksi 1 (JOI 40%) | B99: 45200 | C99: 11.249 | D99: 12.028
A100: Jalan Tol Bayunglencir - Tempino Seksi 1 (JOI 40%) | C100: 0 | D100: 0
A101: Jalan Tol Bayunglencir - Tempino Seksi 1 (JOI 40%) | C101: 0 | D101: 0
A102: Jalan Tol Bocimi Seksi 2 | B102: 44773 | C102: 83.896 | D102: 92.387
A103: Jalan Tol Bocimi Seksi 2 | B103: 44804 | C103: 84.871 | D103: 85.504
A104: Jalan Tol Bocimi Seksi 2 | B104: 44834 | C104: 87.597 | D104: 89.257
A105: Jalan Tol Bocimi Seksi 2 | B105: 44893 | C105: 88.288 | D105: 88.313
A106: Jalan Tol Bocimi Seksi 2 | B106: 44917 | C106: 89.389 | D106: 92.571
A107: Jalan Tol Bocimi Seksi 2 | B107: 44946 | C107: 90.902 | D107: 96.861
A108: Jalan Tol Bocimi Seksi 2 | B108: 44972 | C108: 92.136 | D108: 97.185
A109: Jalan Tol Bocimi Seksi 2 | B109: 44990 | C109: 93.221 | D109: 100
A110: Jalan Tol Bocimi Seksi 2 | B110: 45029 | C110: 94.318 | D110: 95.794
A111: Jalan Tol Bocimi Seksi 2 | B111: 45060 | C111: 94.86 | D111: 98.105
A112: Jalan Tol Bocimi Seksi 2 | B112: 45095 | C112: 95.85 | D112: 99.602
A113: Jalan Tol Bocimi Seksi 2 | B113: 45130 | C113: 96.974 | D113: 99.731
... A152: Jalan Tol IKN 5A Tempadung-Pulau Balang (JOI 50%) | B152: 45660 | C152: 100 | D152: 100
A153: Jalan Tol IKN 5A Tempadung-Pulau Balang (JOI 50%) | C153: 0 | D153: 0
A154: Jalan Tol IKN 5A Tempadung-Pulau Balang (JOI 50%) | C154: 0 | D154: 0
...

Sheet Nama Proyek
A1: No | B1: ID_Project | C1: BU | D1: Nama Proyek | E1: Lat | F1: Long | G1: Koord | H1: Status Project | I1: Panjang | J1: Cesium ION | K1: BimViewer
A2: 1 | B2: 1322032 | C2: Infrastructure II Division | D2: Jalan IKN Lingkar Sepaku Segmen 4 | E2: -0.95259625 | F2: 116.71704 | G2: -0.95259625,116.71704453 | H2: Finish
A3: 2 | B3: 1320027 | C3: Infrastructure II Division | D3: Jalan Sofi - Wayabula 1 | E3: 2.426249 | F3: 128.29766 | G3: 2.426249030,128.29766314 | H3: Finish
A4: 3 | B4: 1417059 | C4: Infrastructure II Division | D4: Jalan Tol Paspro Seksi 4 | E4: -7.8222517 | F4: 113.29968 | G4: -7.82225167,113.29968319 | H4: Finish
A5: 4 | B5: 1322039 | C5: Infrastructure II Division | D5: Rekonstruksi Jl. Kwatisore, Nabire, Papua (JOI 70%) | E5: -3.2507851 | F5: 134.87791 | G5: -3.25078511,134.87791156 | H5: Finish
A6: 5 | B6: 1316019 | C6: Infrastructure II Division | D6: Jalan Tol Bocimi Seksi 2 | E6: -6.8067546 | F6: 106.78537 | G6: -6.80675464,106.785366 | H6: Finish
A7: 6 | B7: 1321025 | C7: Infrastructure II Division | D7: Jalan Long Semamu - Long Bawan 2 (JOP 70%) | E7: 3.7604757 | F7: 115.89978 | G7: 3.76047575,115.89977678 | H7: Finish
A8: 7 | B8: 1317039 | C8: Infrastructure II Division | D8: Jalan Tol Cibitung - Cilincing Seksi 2 | E8: -6.1349105 | F8: 106.93676 | G8: -6.13491053,106.93675986 | H8: Finish
A9: 8 | B9: 1322008 | C9: Infrastructure II Division | D9: Fly Over Simpang Sekip - Palembang (JOI 65%) | E9: -2.952931 | F9: 104.75455 | G9: -2.95293103,104.75455094 | H9: Finish
A10: 9 | B10: 1320031 | C10: Infrastructure II Division | D10: Jalan SP. Blusuh – BTS. Kalteng JOP 62.5 | E10: 3.7627106 | F10: 115.88263 | G10: 3.76271056,115.88262689 | H10: Finish
A11: 10 | B11: 1321047 | C11: Infrastructure II Division | D11: Jalan Akses dan Kawasan Avasta | E11: -6.1296756 | F11: 107.07321 | G11: -6.12967558,107.07321308 | H11: On Hold
A12: 11 | B12: 1316022 | C12: Infrastructure II Division | D12: Jalan Tol Cimanggis Cibitung Seksi 2 | E12: -6.3500801 | F12: 107.02324 | G12: -6.35008011,107.02324233 | H12: Finish
A13: 12 | B13: 1323026 | C13: Infrastructure II Division | D13: Jalan Tol Bayunglencir - Tempino Seksi 1 (JOI 40%) | E13: -1.9839927 | F13: 103.71352 | G13: -1.98399270,103.7135193 | H13: Finish
... A17: 16 | B17: 1324004 | C17: Infrastructure II Division | D17: Jalan Tol IKN Seksi 3B-2 | E17: -1.1373191 | F17: 116.79021 | G17: -1.13731907,116.79020552 | H17: Finish
A18: 17 | B18: 1322033 | C18: Infrastructure II Division | D18: Jalan Tol IKN 5A Tempadung-Pulau Balang (JOI 50%) | E18: -1.1041534 | F18: 116.73424 | G18: -1.10415341,116.73424356 | H18: Finish | K18: "<iframe src='https://bimviewer.org/viewer/?urn=dXJuOmFkc2sub2JqZWN0czpvcy5vYmplY3Q6YXBzLWJpbS12aWV3ZXItYnVja2V0LWNxM3E0NnVrbWdrdHYxdTQ3aTByMHdsYXo5anQ2amF6cHZxeWF5MnVyZXlhNjN1Ni9TT1AlMjAyKzI0MC5ydnQ' style='position: fixed; width:100%; height:100%'></iframe>"
A19: 18 | B19: 1322024 | C19: Infrastructure II Division | D19: Rekonstruksi Jembatan Palu 4 | E19: -0.88562397 | F19: 119.85928 | G19: -0.88562397,119.85928375 | H19: Finish
A20: 19 | B20: 1323023 | C20: Infrastructure II Division | D20: Jalan Distrik (Feeder) IKN (JOI 50%) | E20: -0.9684943 | F20: 116.70188 | G20: -0.96849430,116.70188410 | H20: Finish
A21: 20 | B21: 1323043 | C21: Infrastructure II Division | D21: Pematangan Lahan KIT Batang Klaster 1 Fase 2 Tahap 1 (JOI 40%) | E21: -6.9272374 | F21: 109.95183 | G21: -6.92723742,109.95182730 | H21: Finish
A22: 21 | B22: 1324008 | C22: Infrastructure II Division | D22: Jalan Akses Bandara VVIP IKN (JOI 35%) | E22: -1.1520556 | F22: 116.69317 | G22: -1.15205556,116.69316667 | H22: Finish
A23: 22 | B23: 1319010 | C23: Infrastructure II Division | D23: Jalan Tol Becakayu 2A Ujung | E23: -6.2501111 | F23: 106.99919 | G23: -6.4209386,107.1876008 | H23: Finish
A24: 23 | B24: 1323007 | C24: Infrastructure II Division | D24: Patimban Port Development Paket 5 (JOI member 16%) | E24: -6.2319126 | F24: 107.90813 | G24: -6.23191260,107.90813480 | H24: On Going
A25: 24 | B25: 1323045 | C25: Infrastructure II Division | D25: Jalan Seksi 6C-1 KIPP IKN (JOI 32.50%) | E25: -0.99046214 | F25: 116.69025 | G25: -0.99046214,116.69024762 | H25: Finish
A26: 25 | B26: 1323019 | C26: Infrastructure II Division | D26: Underpass Deltamas SS Sukabungah | E26: -6.4209386 | F26: 107.1876 | G26: -6.42093860,107.18760070 | H26: Finish
A27: 26 | B27: 1323020 | C27: Infrastructure II Division | D27: Jalan Tol Probolinggo Bayuwangi Paket 3 (JOI member 25%) | E27: -7.7264769 | F27: 113.63515 | G27: -7.72647690,113.63515320 | H27: On Going | J27: https://ion.cesium.com/stories/viewer/?id=6d6812ab-f9f1-4950-84d4-65f4f479c8a7
A28: 27 | B28: 1323025 | C28: Infrastructure II Division | D28: Jalan Baru Kretek Girijati (JOI Leader 52.5%) | E28: -8.010033 | F28: 110.33313 | G28: -8.01003300,110.33312900 | H28: On Going
A29: 28 | B29: 1323039 | C29: Infrastructure II Division | D29: Jalan Lot 2 Buluwalang-Sidomulyo-Tambakrejo (JOI 40%) | E29: -8.309619 | F29: 112.11101 | G29: -8.30961900,112.11101000 | H29: On Going
A30: 29 | B30: 1323042 | C30: Infrastructure II Division | D30: Jalan Tol Bocimi Seksi 3A | E30: -6.881205 | F30: 106.78938 | G30: -6.88120502,106.78938277 | H30: On Going | K30: "<iframe src='https://bimviewer.org/viewer/?urn=dXJuOmFkc2sub2JqZWN0czpvcy5vYmplY3Q6YXBzLWJpbS12aWV3ZXItYnVja2V0LWNxM3E0NnVrbWdrdHYxdTQ3aTByMHdsYXo5anQ2amF6cHZxeWF5MnVyZXlhNjN1Ni9KRU1CQVRBTiUyMDE2MCUyMGtvb3JkaW5hdCUyMGJhcnUlMjAyJTIwLSUyMENvcHkucnZ0' style='position: fixed; width:100%; height:100%'></iframe>"
A31: 30 | B31: 1324001 | C31: Infrastructure II Division | D31: Jalan Tol Akses Patimban Paket 2 (JOI 60%) | E31: -6.335333 | F31: 107.77576 | G31: -6.33533300,107.77576100 | H31: On Going
A32: 31 | B32: 1322002 | C32: Infrastructure II Division | D32: Proyek Peningkatan Jalan Sp. Siligita - Kempinski | E32: -8.8056484 | F32: 115.22343 | G32: -6.42093860,107.18760090 | H32: Finish
A33: 31 | B33: 1325012 | C33: Infrastructure II Division | D33: Peningkatan Jalan Paket D KIPP 1C | E33: -1.0121252 | F33: 116.66359 | G33: =CONCATENATE(Table3[[#This Row],[Lat]],",",Table3[[#This Row],[Long]]) -> -1.0121252,116.6635897 | H33: On Going
A34: 32 | B34: 1324010 | C34: Infrastructure II Division | D34: Jalan Tol Bocimi Seksi 3B | E34: -6.881205 | F34: 106.78938 | G34: =CONCATENATE(Table3[[#This Row],[Lat]],",",Table3[[#This Row],[Long]]) -> -6.8812050213,106.7893827682 | H34: On Going
A35: 33 | B35: 1326001 | C35: Infrastructure II Division | D35: Jembatan Kalimantan-Pulau Laut(JOI 20%) | E35: -3.471378 | F35: 116.02859 | G35: =CONCATENATE(Table3[[#This Row],[Lat]],",",Table3[[#This Row],[Long]]) -> -3.471378,116.028586 | H35: On Going
A36: 34 | C36: Infrastructure II Division | D36: Perbaikan Geometrik Jalan Mengwitani Singaraja | E36: -8.199858 | F36: 115.1423 | G36: =CONCATENATE(Table3[[#This Row],[Lat]],",",Table3[[#This Row],[Long]]) -> -8.199858,115.1423 | H36: On Going
A37: 35 | C37: Infrastructure II Division | D37: Pembangunan Jalan Kompleks Kawasan Yudikatif IKN | E37: -0.964223 | F37: 116.69809 | G37: =CONCATENATE(Table3[[#This Row],[Lat]],",",Table3[[#This Row],[Long]]) -> -0.964223,116.698095 | H37: On Going

Sheet Sheet3
A1: Jalan Tol Japek 2 Selatan Paket 3 Induk | B1: -6.42873464,107.19897003 | C1: On Going | D1: -6.4287346 | E1: 107.19897
A2: Jalan Tol Bocimi Seksi 2 | B2: -6.80675464,106.785366 | C2: Finish | D2: -6.8067546 | E2: 106.78537
A3: Jalan Jalan Tol Cimanggis Cibitung Seksi 2 | B3: -6.35008011,107.02324233 | C3: Finish | D3: -6.3500801 | E3: 107.02324
A4: Jalan Tol Cibitung - Cilincing Seksi 2 | B4: -6.13491053,106.93675986 | C4: Finish | D4: -6.1349105 | E4: 106.93676
A5: Jalan Tol Paspro Seksi 4 | B5: -7.82225167,113.29968319 | C5: Finish | D5: -7.8222517 | E5: 113.29968
A6: Jalan Sofi - Wayabula 1 | B6: 2.42624903,128.29766314 | C6: Finish | D6: 2.426249 | E6: 128.29766
A7: Jalan SP. Blusuh – BTS. Kalteng JOP 62.5 | B7: 3.76271056,115.88262689 | C7: Finish | D7: 3.7627106 | E7: 115.88263
A8: Jalan dan Jembatan Batas Kab. Blitar Lot 6B | B8: -8.29394978,112.00545006 | C8: Finish | D8: -8.2939498 | E8: 112.00545
A9: Jalan Akses dan Kawasan Avasta | B9: -6.12967558,107.07321308 | C9: On Hold | D9: -6.1296756 | E9: 107.07321
A10: Fly Over Simpang Sekip - Palembang JOI 65% | B10: -2.95293103,104.75455094 | C10: Finish | D10: -2.952931 | E10: 104.75455
A11: Rekonstruksi Jembatan Palu 4 | B11: -0.88562397,119.85928375 | C11: Finish | D11: -0.88562397 | E11: 119.85928
A12: Jalan Tol IKN Tempadung-Pulau Balang (JOI 50%) | B12: -1.104153412,116.73424356 | C12: Finish | D12: -1.1041534 | E12: 116.73424
... A28: Peningkatan Jalan Paket D KIPP 1C | B28: -1.01212520,116.66358970 | C28: On Going | D28: -1.0121252 | E28: 116.66359

Sheet Sheet4
A1: item
A2: Nama Proyek
A3: Pengguna Jasa
A4: Lokasi Proyek
A5: Tanggal SPMK
A6: Jangka Waktu Pelaksanaan
A7: Masa Pemeliharaan
A8: Jenis Kontrak
A9: Cara Pembayaran
A10: Nilai Kontrak
A11: Retensi
A12: Kontraktor Pelaksana
A13: Lingkup Pekerjaan

Sheet Informasi Umum 2
A1: Nama Proyek | B1: Nama Proyek | C1: Pengguna Jasa | D1: Lokasi Proyek | E1: Tanggal SPMK | F1: Jangka Waktu Pelaksanaan | G1: Masa Pemeliharaan | H1: Jenis Kontrak | I1: Cara Pembayaran | J1: Nilai Kontrak | K1: Retensi | L1: Kontraktor Pelaksana | M1: Lingkup Pekerjaan
A2: =Table2[[#This Row],[Nama Proyek]] -> Jalan Tol Bocimi Seksi 3 | B2: Pembangunan Jalan Tol Ciawi - Sukabumi Seksi 3 STA 26+500 sd 40+200, 13,7 km | C2: PT Trans Jabar Tol | D2: Kab Sukabumi, Prov Jawa Barat | E2: 45257 | F2: 731 Hari Kalender | G2: 1095 Hari Kalender | H2: Fixed Unit Price | I2: Sertifikat Bulanan | J2: Rp 1876743479356 (NK + PPn 11%) | K2: 0.05 | L2: PT Waskita Karya (Persero) | M2: 0
A3: Jalan Lot 2 Buluwalang-Sidomulyo-Tambakrejo (JOI 40%) | B3: Pembangunan Jalan Lintas Selatan Lot 2:Bululawang - Sidomulyo - Tambakrejo | C3: Satker Pelaksanaan Jalan Nasional Wilayah II Prov. Jawa Timur Pejabat Pembuat Komitmen 2.7 Provinsi Jawa Timur | D3: Kab. Blitar, Prov. Jawa Timur | E3: 45226 | F3: 1020 Hari Kalender dari SPMK | G3: 365 Hari Kalender | H3: Unit Price | I3: Interim Payment Certificate (Monthly Payment) | J3: 316419029407 | K3: 0 | L3: PP - WASKITA - SMU | M3: Panjang 12.775km; Box Culvert 23 unit; Jembatan (30m) 3 unit
A4: Jalan Distrik (Feeder) IKN (JOI 50%) | B4: Pembangunan Jalan di dalam KIPP: Paket Pembangunan Jalan Feeder (Distrik) di Kawasan IKN | C4: Kementerian PUPR Direktorat Jendral Bina Marga | D4: Kabupaten Penajam Paser Utara, Prov. Kalimantan Timur | E4: 45112 | F4: 11 Juli 2023 sd 04 Agustus 2024 (390 hari kalender) | G4: 365 Hari Kalender | H4: Unit Price | I4: Sertifikat Bulanan | J4: 1160870287394 | K4: 0 | L4: Waskita - Nindya - Permata KSO | M4: Pembangunan dan pembukaan jalan baru di KIPP 10.30km; 1 jembatan; Multi Utility Tunnel (MUT) 8.37km; Box Culvert 26 buah
A5: Jalan Baru Kretek Girijati (JOI Leader 52.5%) | B5: Jalan Kretek - Girijati (JOI 52.5%) | C5: Kementerian PUPR Direktorat Jendral Bina Marga PPK DI Yogyakarta | D5: Prov. DI Yogyakarta | E5: 45140 | F5: 02 Agustus 2023 sd 22 Juli 2025 (720 hari kalender) | G5: 365 Hari Kalender | H5: Unit Price | I5: Sertifikat Bulanan | J5: 241031298951 | K5: 0 | L5: Waskita - PP | M5: 0
A6: Jalan Seksi 6C-1 KIPP IKN (JOI 32.50%) | B6: Jalan IKN Seksi 6C-1 (JOI 32.5%) | C6: Kementerian PUPR Direktorat Jendral Bina Marga Balai Besar Pelaksanaan | D6: Provinsi Kalimantan Timur | E6: 45267 | F6: 7 Desember 2023 sd 30 Desember 2024 (389 Hari Kalender) | G6: 365 Hari Kalender | H6: Unit Price | I6: Monthly Payment | J6: 1493278263794 | K6: 0 | L6: PP - WASKITA - Yasa Patria Perkasa | M6: 0
A7: Pematangan Lahan KIT Batang Klaster 1 Fase 2 Tahap 1 (JOI 40%) | B7: Pematangan Lahan KITB JOI 40% | C7: PPK Kasawan Industri Batang I, BBPJN Jawa Tengah - DIY, PUPR Bina Marga | D7: Kabupaten Batang, Prov. Jawa Tengah | E7: 45239 | F7: 9 November 2023 sd 3 September 2024 (300 hari Kalender) | G7: 180 hari kalender | H7: Unit Price | I7: Monthly Payment | J7: 463336549270 | K7: 0 | L7: Nindya Karya - Waskita Karya - Bina Nusa Lestari | M7: 0
A8: Jalan Tol Probolinggo Bayuwangi Paket 3 (JOI member 25%) | B8: Probolinggo - Banyuwangi Paket 3 (JOP 25%) | C8: PT. Jasamarga Probolinggo - Banyuwangi | D8: Provinsi Jawa Timur | E8: 44978 | F8: 12 Juni 2023 sd 12 Desember 2024 (549 hari Kalender) | G8: 13 Desember 2024 sd 12 Desember 2026 (1095 Hari Kalender) | H8: Gabungan Lumpsum dan Unit Price | I8: Monthly Payment | J8: 3987286153268 | L8: PP - Waskita Karya - Wijaya Karya | M8: 0
A9: Underpass Deltamas SS Sukabungah | B9: Akses Jalan Tol Japek Selatan (Deltamas) | C9: PT. Puradelta Lestari | D9: Kab. Bekasi, Prov. Jawa Barat | E9: 45097 | F9: 26 Juni 2023 sd 23 Desember 2023 (180 hari kalender) | G9: 1095 Hari Kalender | H9: Unit Price | I9: Sertifikat Bulanan | J9: 100900000000 | K9: 0 | L9: Waskita Karya | M9: STA 4+400 - 5+000 (600m)
A10: Fly Over Simpang Sekip - Palembang (JOI 65%) | B10: Pembangunan FO Sekip Ujung | C10: PPK 3.6 Provinsi Sumatera Selatan | D10: Palembang, Prov. Sumatera Selatan | F10: 630 hari kalender | G10: 0 | H10: 0 | I10: Sertifikat Bulanan | J10: 152943426000 | K10: 0 | L10: Waskita - Kencana KSO | M10: STA 0+000 - 0+660 (660m)
A11: Patimban Port Development Paket 5 (JOI member 16%) | B11: Patimban Port Development Project Package 5: Car Terminal Construction | C11: Kementerian Perhubungan - Dirjen Perhubungan Laut | D11: Kab. Subang, Provinsi Jawa Barat | E11: 45016 | F11: 730 hari kalender dari tanggal SPMK | G11: 0 | H11: Unit Price | I11: Monthly Payment | J11: 2383566664079 | K11: 0 | L11: TOA - Waskita - Wakachiku - HK - Abipraya | M11: 0
A12: Jalan Akses Bandara VVIP IKN (JOI 35%) | B12: Jalan Akses Bandara VVIP IKN (JOI 35%) | C12: Kementerian PUPR Direktorat Jenderal Bina Marga Balai | D12: Provinsi Kalimantan Timur | E12: 45306 | F12: 16 Januari s.d. 31 Desember 2024 (350 hari) | G12: 365 hari kalender | H12: Unit Price | I12: Monthly Payment | J12: 853785920150 | K12: 0 | L12: Nindya Karya - Waskita Karya - Naviri Multi Konstruksi - Panca Karya Sentosa | M12: Jalan Akses 1.74km; Interchange 6 ramp; Jalan Provinsi 850m
A13: Jalan Tol Bayunglencir - Tempino Seksi 1 (JOI 40%) | B13: Jalan Tol Bayunglencir - Tempino Seksi 1 (JOI 40%) | C13: PPK 1.1 Satuan Kerja PJN Wilayah Provinsi Sumatera Utara | D13: Provinsi Jambi | E13: 45063 | F13: 27 Mei 2023 s.d 30 Juni 2024 (520 hari) | G13: 365 hari kalender | H13: Gabungan lumpsum dan unit price | I13: Monthly Payment | J13: 1455374902280 | K13: 0 | L13: Adhi Karya - Waskita Karya - Jaya Konstruksi | M13: Mainroan 7.625km; Akses tol 2.90km
A14: Jalan Tol IKN Seksi 3B-2 | B14: Tol IKN Seksi 3B-2 JOI 20% | C14: Kementerian PUPR Direktorat Jenderal Bina Marga Balai Pelaksana Jalan Nasional Kalimantan Timur | D14: Balikpapan, Prov. Kalimantan Timur | E14: 45281 | F14: 21 Desember 2023 - 12 Juni 2025 (539 hari kalender) | G14: 365 hari kalender | H14: Unit Price | I14: Monthly Payment | J14: 2399426628007 | K14: 0 | L14: Wijaya Karya - Waskita Karya - Jaya Konstruksi - PP | M14: Elevated pile slab 1.26km; interchange KKT Kariangau 1 lokasi; Jembatan satwa 2 lokasi
A15: Jalan Tol Akses Patimban Paket 2 (JOI 60%) | B15: Pembangunan Jalan Tol Akses Patimban Paket 2 | C15: Kementerian PUPR Dirjen Bina Marga | D15: Kab. Subang, Prov. Jawa Barat | F15: 3 Januari 2024 - 02 Desember 2025 (700 hari Kalender) | G15: 365 hari kalender | H15: 0 | I15: Sertifikat Bulanan | J15: 8.7353754e+11 | K15: 0 | L15: Waskita - Abipraya | M15: Civil works main road 6.2KM (STA 21+800 - 28+000), 5 bridge, 1 overpass
A16: Rekonstruksi Jl. Kwatisore, Nabire, Papua (JOI 70%) | B16: Pekerjaan Rekonstruksi Jalan Kwatisore-Kaamp. Muri (Bts Provinsi Papua Barat) I | C16: Dirjen Binamarga Pelaksanaan Jalan Nasional Wilayah VII Provinsi Papua (Nabire) | D16: Kabupaten Nabire, Provinsi Papua | F16: 510 hari kalender | G16: 365 hari kalender | H16: Unit Price | I16: Monthly Payment | J16: 1.3297678e+11 | K16: 0 | L16: Waskita - Karya Mandiri Permai KSO | M16: Pembangunan Jalan sampai perkerasan panjang 16.45 km (KM 113+420 sd 121+300 dan KM 129+700 sd 138+200)
A17: Jalan IKN Lingkar Sepaku Segmen 4 (JOI 70%) | B17: Jalan IKN Sepaku Segmen 4 JOI 70% | C17: Kementerian PUPR – BBPJN Kalimantan Timur – Satuan Kerja Pelaksanaan Pembangunan IKN 2 | D17: Penajam Paser Utara, Kalimantan Timur | E17: 44802 | F17: 19/09/2022 – 04/05/2024 (594 hari) | G17: 182 hari | H17: Fix Unit Price | I17: Monthly Payment | J17: 1.7990525e+11 | K17: 0 | L17: 0 | M17: 0
A18: Jalan Tol IKN 5A Tempadung-Pulau Balang (JOI 50%) | B18: Jalan Tol IKN Segmen Sp. Tempadung - Jemb. Pulau Balang (JOI 50%) | C18: Kementerian PUPR | D18: Tempadung-Pulau Balang, Kalimantan Timur | E18: 44813 | F18: 730 hari | G18: 0 | I18: Monthly Payment | J18: 2.1982553e+12 | L18: Waskita- Nindya - Modern KSO | M18: Jalan 4.755km; elevated pile slab 1.380 (7 lokasi); jjembatan 2 buah; Box Culvert 12 buah
A19: Rekonstruksi Jembatan Palu 4 | B19: Rekonstruksi Jembatan Palu 4 | C19: Tokyu Construction Co., Ltd. | D19: Palu, Sulawesi Tengah | E19: 44734 | F19: 730 hari (s.d. 30 Juni 2024) | G19: 365 hari kalender | H19: Lumpsum | I19: Monthly Payment with Minimum Progress | J19: 1787000000 | K19: 0 | L19: 0 | M19: Jembatan dan pendekat (380+250+410m).
A20: Jalan Tol Cibitung - Cilincing Seksi 2 | B20: Cimanggis - Cibitung Seksi 2 | C20: PT. Cimanggis Cibitung Tollways | D20: Bogor, Bekasi,Prov. Jawa Barat | E20: 42547 | F20: sd Mei 2024 (Cikeas - Cibitung) | G20: 1095 hari kalender | H20: Fixed Unit Price | I20: Termin | J20: 3.8280372e+12 | K20: 0 | L20: PT. Waskita Karya | M20: Jalan Tol
A21: Jalan Tol Serang - Panimbang Seksi III Fase 2 Paket 3 | B21: Proyek Jalan Tol Serang - Penimbang Seksi 3 JOI 27.5% | C21: Satker JBH Serang - Panimbang, Balai Prov Banten, Kementerian PUPR | D21: Kab. Pandeglang, Prov. Banten | E21: 45268 | F21: 390 hari kalender setelah SPMK terbit | G21: 365 hari kalender | H21: Kontrak Harga Satuan | I21: Sertifikat Bulanan | J21: 1915188111950 | K21: 0 | L21: PP - Adhi Karya - Waskita Karya - Modern | M21: Jalan Tol
A22: Proyek Peningkatan Jalan Sp. Siligita - Kempinski | B22: Peningkatan Jalan Sp. Siligita-Kempinski, Showcase Mangrove | C22: Kementerian PUPR, Ditjen Binamarga, Balai Besar Pelaksanaan Jalan Nasional Jawa Timur & Bali | D22: Nusa Dua, Prov. Bali | E22: 44673 | F22: Februari 2022 sd September 2022 | G22: 0 | H22: Fix Unit Price | I22: Monthly Payment | J22: 1.2000283e+11 | K22: 0 | L22: PT. Waskita Karya | M22: 5.225 KM (Sp Siligita - Kempinski) dan 1.5km (Showcase Mangrove)

Sheet Informasi Umum
A1: No | B1: Item | C1: Deskripsi | D1: Nama Proyek | E1: ID_Project
A2: 1 | B2: Nama Proyek | C2: Pembangunan Jalan Tol Ciawi - Sukabumi Seksi 3 STA 26+500 sd 40+200, 13,7 km | D2: Jalan Tol Bocimi Seksi 3 | E2: 1323042
A3: 2 | B3: Pengguna Jasa | C3: PT Trans Jabar Tol | D3: Jalan Tol Bocimi Seksi 3 | E3: 1323042
A4: 3 | B4: Lokasi Proyek | C4: Kab Sukabumi, Prov Jawa Barat | D4: Jalan Tol Bocimi Seksi 3 | E4: 1323042
A5: 4 | B5: Tanggal SPMK | C5: 27 November 2023 | D5: Jalan Tol Bocimi Seksi 3 | E5: 1323042
A6: 5 | B6: Jangka Waktu Pelaksanaan | C6: 731 Hari Kalender | D6: Jalan Tol Bocimi Seksi 3 | E6: 1323042
A7: 6 | B7: Masa Pemeliharaan | C7: 1095 Hari Kalender | D7: Jalan Tol Bocimi Seksi 3 | E7: 1323042
A8: 7 | B8: Jenis Kontrak | C8: Fixed Unit Price | D8: Jalan Tol Bocimi Seksi 3 | E8: 1323042
A9: 8 | B9: Cara Pembayaran | C9: Sertifikat Bulanan | D9: Jalan Tol Bocimi Seksi 3 | E9: 1323042
A10: 9 | B10: Nilai Kontrak | C10: Rp 1.876.743.479.356 (NK + PPn 11%) | D10: Jalan Tol Bocimi Seksi 3 | E10: 1323042
A11: 10 | B11: Retensi | C11: 5% | D11: Jalan Tol Bocimi Seksi 3 | E11: 1323042
A12: 11 | B12: Kontraktor Pelaksana | C12: PT Waskita Karya (Persero) | D12: Jalan Tol Bocimi Seksi 3 | E12: 1323042
A13: 12 | B13: Lingkup Pekerjaan | D13: Jalan Tol Bocimi Seksi 3 | E13: 1323042
A14: 1 | B14: Nama Proyek | C14: Pembangunan Jalan Lintas Selatan Lot 2:Bululawang - Sidomulyo - Tambakrejo | D14: Jalan Lot 2 Buluwalang-Sidomulyo-Tambakrejo (JOI 40%) | E14: 1323039
A15: 2 | B15: Pengguna Jasa | C15: Satker Pelaksanaan Jalan Nasional Wilayah II Prov. Jawa Timur Pejabat Pembuat Komitmen 2.7 Provinsi Jawa Timur | D15: Jalan Lot 2 Buluwalang-Sidomulyo-Tambakrejo (JOI 40%) | E15: 1323039
A16: 3 | B16: Lokasi Proyek | C16: Kab. Blitar, Prov. Jawa Timur | D16: Jalan Lot 2 Buluwalang-Sidomulyo-Tambakrejo (JOI 40%) | E16: 1323039
A17: 4 | B17: Tanggal SPMK | C17: 27 Oktober 2023 | D17: Jalan Lot 2 Buluwalang-Sidomulyo-Tambakrejo (JOI 40%) | E17: 1323039
A18: 5 | B18: Jangka Waktu Pelaksanaan | C18: 1020 Hari Kalender dari SPMK | D18: Jalan Lot 2 Buluwalang-Sidomulyo-Tambakrejo (JOI 40%) | E18: 1323039
A19: 6 | B19: Masa Pemeliharaan | C19: 365 Hari Kalender | D19: Jalan Lot 2 Buluwalang-Sidomulyo-Tambakrejo (JOI 40%) | E19: 1323039
A20: 7 | B20: Jenis Kontrak | C20: Unit Price | D20: Jalan Lot 2 Buluwalang-Sidomulyo-Tambakrejo (JOI 40%) | E20: 1323039
A21: 8 | B21: Cara Pembayaran | C21: Interim Payment Certificate (Monthly Payment) | D21: Jalan Lot 2 Buluwalang-Sidomulyo-Tambakrejo (JOI 40%) | E21: 1323039
A22: 9 | B22: Nilai Kontrak | C22: Rp 316.419.029.407 | D22: Jalan Lot 2 Buluwalang-Sidomulyo-Tambakrejo (JOI 40%) | E22: 1323039
A23: 10 | B23: Retensi | D23: Jalan Lot 2 Buluwalang-Sidomulyo-Tambakrejo (JOI 40%) | E23: 1323039
A24: 11 | B24: Kontraktor Pelaksana | C24: PP - WASKITA - SMU | D24: Jalan Lot 2 Buluwalang-Sidomulyo-Tambakrejo (JOI 40%) | E24: 1323039
A25: 12 | B25: Lingkup Pekerjaan | C25: Panjang 12.775km; Box Culvert 23 unit; Jembatan (30m) 3 unit | D25: Jalan Lot 2 Buluwalang-Sidomulyo-Tambakrejo (JOI 40%) | E25: 1323039
A26: 1 | B26: Nama Proyek | C26: Pembangunan Jalan di dalam KIPP: Paket Pembangunan Jalan Feeder (Distrik) di Kawasan IKN | D26: Jalan Distrik (Feeder) IKN (JOI 50%) | E26: 1323025
A27: 2 | B27: Pengguna Jasa | C27: Kementerian PUPR Direktorat Jendral Bina Marga | D27: Jalan Distrik (Feeder) IKN (JOI 50%) | E27: 1323025
A28: 3 | B28: Lokasi Proyek | C28: Kabupaten Penajam Paser Utara, Prov. Kalimantan Timur | D28: Jalan Distrik (Feeder) IKN (JOI 50%) | E28: 1323025
A29: 4 | B29: Tanggal SPMK | C29: 5 Juli 2023 | D29: Jalan Distrik (Feeder) IKN (JOI 50%) | E29: 1323025
A30: 5 | B30: Jangka Waktu Pelaksanaan | C30: 11 Juli 2023 sd 04 Agustus 2024 (390 hari kalender) | D30: Jalan Distrik (Feeder) IKN (JOI 50%) | E30: 1323025
A31: 6 | B31: Masa Pemeliharaan | C31: 365 Hari Kalender | D31: Jalan Distrik (Feeder) IKN (JOI 50%) | E31: 1323025
A32: 7 | B32: Jenis Kontrak | C32: Unit Price | D32: Jalan Distrik (Feeder) IKN (JOI 50%) | E32: 1323025
A33: 8 | B33: Cara Pembayaran | C33: Sertifikat Bulanan | D33: Jalan Distrik (Feeder) IKN (JOI 50%) | E33: 1323025
A34: 9 | B34: Nilai Kontrak | C34: Rp 1.160.870.287.394 | D34: Jalan Distrik (Feeder) IKN (JOI 50%) | E34: 1323025
A35: 10 | B35: Retensi | D35: Jalan Distrik (Feeder) IKN (JOI 50%) | E35: 1323025
A36: 11 | B36: Kontraktor Pelaksana | C36: Waskita - Nindya - Permata KSO | D36: Jalan Distrik (Feeder) IKN (JOI 50%) | E36: 1323025
A37: 12 | B37: Lingkup Pekerjaan | C37: Pembangunan dan pembukaan jalan baru di KIPP 10.30km; 1 jembatan; Multi Utility Tunnel (MUT) 8.37km; Box Culvert 26 buah | D37: Jalan Distrik (Feeder) IKN (JOI 50%) | E37: 1323025
A38: 1 | B38: Nama Proyek | C38: Jalan Kretek - Girijati (JOI 52.5%) | D38: Jalan Baru Kretek Girijati (JOI Leader 52.5%) | E38: 1323026
A39: 2 | B39: Pengguna Jasa | C39: Kementerian PUPR Direktorat Jendral Bina Marga PPK DI Yogyakarta | D39: Jalan Baru Kretek Girijati (JOI Leader 52.5%) | E39: 1323026
A40: 3 | B40: Lokasi Proyek | C40: Prov. DI Yogyakarta | D40: Jalan Baru Kretek Girijati (JOI Leader 52.5%) | E40: 1323026
A41: 4 | B41: Tanggal SPMK | C41: 02 Agustus 2023 | D41: Jalan Baru Kretek Girijati (JOI Leader 52.5%) | E41: 1323026
A42: 5 | B42: Jangka Waktu Pelaksanaan | C42: 02 Agustus 2023 sd 22 Juli 2025 (720 hari kalender) | D42: Jalan Baru Kretek Girijati (JOI Leader 52.5%) | E42: 1323026
A43: 6 | B43: Masa Pemeliharaan | C43: 365 Hari Kalender | D43: Jalan Baru Kretek Girijati (JOI Leader 52.5%) | E43: 1323026
A44: 7 | B44: Jenis Kontrak | C44: Unit Price | D44: Jalan Baru Kretek Girijati (JOI Leader 52.5%) | E44: 1323026
A45: 8 | B45: Cara Pembayaran | C45: Sertifikat Bulanan | D45: Jalan Baru Kretek Girijati (JOI Leader 52.5%) | E45: 1323026
A46: 9 | B46: Nilai Kontrak | C46: Rp 241.031.298.951 | D46: Jalan Baru Kretek Girijati (JOI Leader 52.5%) | E46: 1323026
A47: 10 | B47: Retensi | D47: Jalan Baru Kretek Girijati (JOI Leader 52.5%) | E47: 1323026
A48: 11 | B48: Kontraktor Pelaksana | C48: Waskita - PP | D48: Jalan Baru Kretek Girijati (JOI Leader 52.5%) | E48: 1323026
A49: 12 | B49: Lingkup Pekerjaan | D49: Jalan Baru Kretek Girijati (JOI Leader 52.5%) | E49: 1323026
A50: 1 | B50: Nama Proyek | C50: Jalan IKN Seksi 6C-1 (JOI 32.5%) | D50: Jalan Seksi 6C-1 KIPP IKN (JOI 32.50%) | E50: 1323045
A51: 2 | B51: Pengguna Jasa | C51: Kementerian PUPR Direktorat Jendral Bina Marga Balai Besar Pelaksanaan | D51: Jalan Seksi 6C-1 KIPP IKN (JOI 32.50%) | E51: 1323045
A52: 3 | B52: Lokasi Proyek | C52: Provinsi Kalimantan Timur | D52: Jalan Seksi 6C-1 KIPP IKN (JOI 32.50%) | E52: 1323045
A53: 4 | B53: Tanggal SPMK | C53: 7 Desember 2023 | D53: Jalan Seksi 6C-1 KIPP IKN (JOI 32.50%) | E53: 1323045
A54: 5 | B54: Jangka Waktu Pelaksanaan | C54: 7 Desember 2023 sd 30 Desember 2024 (389 Hari Kalender) | D54: Jalan Seksi 6C-1 KIPP IKN (JOI 32.50%) | E54: 1323045
A55: 6 | B55: Masa Pemeliharaan | C55: 365 Hari Kalender | D55: Jalan Seksi 6C-1 KIPP IKN (JOI 32.50%) | E55: 1323045
A56: 7 | B56: Jenis Kontrak | C56: Unit Price | D56: Jalan Seksi 6C-1 KIPP IKN (JOI 32.50%) | E56: 1323045
A57: 8 | B57: Cara Pembayaran | C57: Monthly Payment | D57: Jalan Seksi 6C-1 KIPP IKN (JOI 32.50%) | E57: 1323045
A58: 9 | B58: Nilai Kontrak | C58: Rp 1.493.278.263.794 | D58: Jalan Seksi 6C-1 KIPP IKN (JOI 32.50%) | E58: 1323045
A59: 10 | B59: Retensi | D59: Jalan Seksi 6C-1 KIPP IKN (JOI 32.50%) | E59: 1323045
A60: 11 | B60: Kontraktor Pelaksana | C60: PP - WASKITA - Yasa Patria Perkasa | D60: Jalan Seksi 6C-1 KIPP IKN (JOI 32.50%) | E60: 1323045
A61: 12 | B61: Lingkup Pekerjaan | D61: Jalan Seksi 6C-1 KIPP IKN (JOI 32.50%) | E61: 1323045
A62: 1 | B62: Nama Proyek | C62: Pematangan Lahan KITB JOI 40% | D62: Pematangan Lahan KIT Batang Klaster 1 Fase 2 Tahap 1 (JOI 40%) | E62: 1323043
A63: 2 | B63: Pengguna Jasa | C63: PPK Kasawan Industri Batang I, BBPJN Jawa Tengah - DIY, PUPR Bina Marga | D63: Pematangan Lahan KIT Batang Klaster 1 Fase 2 Tahap 1 (JOI 40%) | E63: 1323043
A64: 3 | B64: Lokasi Proyek | C64: Kabupaten Batang, Prov. Jawa Tengah | D64: Pematangan Lahan KIT Batang Klaster 1 Fase 2 Tahap 1 (JOI 40%) | E64: 1323043
A65: 4 | B65: Tanggal SPMK | C65: 45239 | D65: Pematangan Lahan KIT Batang Klaster 1 Fase 2 Tahap 1 (JOI 40%) | E65: 1323043
A66: 5 | B66: Jangka Waktu Pelaksanaan | C66: 9 November 2023 sd 3 September 2024 (300 hari Kalender) | D66: Pematangan Lahan KIT Batang Klaster 1 Fase 2 Tahap 1 (JOI 40%) | E66: 1323043
A67: 6 | B67: Masa Pemeliharaan | C67: 180 hari kalender | D67: Pematangan Lahan KIT Batang Klaster 1 Fase 2 Tahap 1 (JOI 40%) | E67: 1323043
A68: 7 | B68: Jenis Kontrak | C68: Unit Price | D68: Pematangan Lahan KIT Batang Klaster 1 Fase 2 Tahap 1 (JOI 40%) | E68: 1323043
A69: 8 | B69: Cara Pembayaran | C69: Monthly Payment | D69: Pematangan Lahan KIT Batang Klaster 1 Fase 2 Tahap 1 (JOI 40%) | E69: 1323043
A70: 9 | B70: Nilai Kontrak | C70: Rp 463.336.549.270 | D70: Pematangan Lahan KIT Batang Klaster 1 Fase 2 Tahap 1 (JOI 40%) | E70: 1323043
A71: 10 | B71: Retensi | D71: Pematangan Lahan KIT Batang Klaster 1 Fase 2 Tahap 1 (JOI 40%) | E71: 1323043
A72: 11 | B72: Kontraktor Pelaksana | C72: Nindya Karya - Waskita Karya - Bina Nusa Lestari | D72: Pematangan Lahan KIT Batang Klaster 1 Fase 2 Tahap 1 (JOI 40%) | E72: 1323043
A73: 12 | B73: Lingkup Pekerjaan | D73: Pematangan Lahan KIT Batang Klaster 1 Fase 2 Tahap 1 (JOI 40%) | E73: 1323043
A74: 1 | B74: Nama Proyek | C74: Probolinggo - Banyuwangi Paket 3 (JOP 25%) | D74: Jalan Tol Probolinggo Bayuwangi Paket 3 (JOI member 25%) | E74: 1323020
A75: 2 | B75: Pengguna Jasa | C75: PT. Jasamarga Probolinggo - Banyuwangi | D75: Jalan Tol Probolinggo Bayuwangi Paket 3 (JOI member 25%) | E75: 1323020
A76: 3 | B76: Lokasi Proyek | C76: Provinsi Jawa Timur | D76: Jalan Tol Probolinggo Bayuwangi Paket 3 (JOI member 25%) | E76: 1323020
A77: 4 | B77: Tanggal SPMK | C77: 21 Februari 2023 | D77: Jalan Tol Probolinggo Bayuwangi Paket 3 (JOI member 25%) | E77: 1323020
A78: 5 | B78: Jangka Waktu Pelaksanaan | C78: 12 Juni 2023 sd 12 Desember 2024 (549 hari Kalender) | D78: Jalan Tol Probolinggo Bayuwangi Paket 3 (JOI member 25%) | E78: 1323020
A79: 6 | B79: Masa Pemeliharaan | C79: 13 Desember 2024 sd 12 Desember 2026 (1095 Hari Kalender) | D79: Jalan Tol Probolinggo Bayuwangi Paket 3 (JOI member 25%) | E79: 1323020
A80: 7 | B80: Jenis Kontrak | C80: Gabungan Lumpsum dan Unit Price | D80: Jalan Tol Probolinggo Bayuwangi Paket 3 (JOI member 25%) | E80: 1323020
A81: 8 | B81: Cara Pembayaran | C81: Monthly Payment | D81: Jalan Tol Probolinggo Bayuwangi Paket 3 (JOI member 25%) | E81: 1323020
A82: 9 | B82: Nilai Kontrak | C82: Rp 3.987.286.153.268 | D82: Jalan Tol Probolinggo Bayuwangi Paket 3 (JOI member 25%) | E82: 1323020
A83: 10 | B83: Retensi | D83: Jalan Tol Probolinggo Bayuwangi Paket 3 (JOI member 25%) | E83: 1323020
A84: 11 | B84: Kontraktor Pelaksana | C84: PP - Waskita Karya - Wijaya Karya | D84: Jalan Tol Probolinggo Bayuwangi Paket 3 (JOI member 25%) | E84: 1323020
A85: 12 | B85: Lingkup Pekerjaan | D85: Jalan Tol Probolinggo Bayuwangi Paket 3 (JOI member 25%) | E85: 1323020
A86: 1 | B86: Nama Proyek | C86: Akses Jalan Tol Japek Selatan (Deltamas) | D86: Underpass Deltamas SS Sukabungah | E86: 1323023
A87: 2 | B87: Pengguna Jasa | C87: PT. Puradelta Lestari | D87: Underpass Deltamas SS Sukabungah | E87: 1323023
A88: 3 | B88: Lokasi Proyek | C88: Kab. Bekasi, Prov. Jawa Barat | D88: Underpass Deltamas SS Sukabungah | E88: 1323023
A89: 4 | B89: Tanggal SPMK | C89: 20 Juni 2023 | D89: Underpass Deltamas SS Sukabungah | E89: 1323023
A90: 5 | B90: Jangka Waktu Pelaksanaan | C90: 26 Juni 2023 sd 23 Desember 2023 (180 hari kalender) | D90: Underpass Deltamas SS Sukabungah | E90: 1323023
A91: 6 | B91: Masa Pemeliharaan | C91: 1095 Hari Kalender | D91: Underpass Deltamas SS Sukabungah | E91: 1323023
A92: 7 | B92: Jenis Kontrak | C92: Unit Price | D92: Underpass Deltamas SS Sukabungah | E92: 1323023
A93: 8 | B93: Cara Pembayaran | C93: Sertifikat Bulanan | D93: Underpass Deltamas SS Sukabungah | E93: 1323023
A94: 9 | B94: Nilai Kontrak | C94: Rp 100.900.000.000 | D94: Underpass Deltamas SS Sukabungah | E94: 1323023
A95: 10 | B95: Retensi | D95: Underpass Deltamas SS Sukabungah | E95: 1323023
A96: 11 | B96: Kontraktor Pelaksana | C96: Waskita Karya | D96: Underpass Deltamas SS Sukabungah | E96: 1323023
A97: 12 | B97: Lingkup Pekerjaan | C97: STA 4+400 - 5+000 (600m) | D97: Underpass Deltamas SS Sukabungah | E97: 1323023
A98: 1 | B98: Nama Proyek | C98: Pembangunan FO Sekip Ujung | D98: Fly Over Simpang Sekip - Palembang (JOI 65%) | E98: 1322008
A99: 2 | B99: Pengguna Jasa | C99: PPK 3.6 Provinsi Sumatera Selatan | D99: Fly Over Simpang Sekip - Palembang (JOI 65%) | E99: 1322008
A100: 3 | B100: Lokasi Proyek | C100: Palembang, Prov. Sumatera Selatan | D100: Fly Over Simpang Sekip - Palembang (JOI 65%) | E100: 1322008
...
